{
  "timestamp": 1782030165,
  "updated_at": "2026-06-21 08:22:45 UTC",
  "num_offers": 108,
  "active_offers": 53,
  "unique_makers": 87,
  "unique_pairs": 19,
  "last_bsx_msg_ts": 1782030047,
  "stats": {
    "msgs_received": 299,
    "msgs_decrypted": 264,
    "offers_parsed": 179,
    "decrypt_errors": 35,
    "not_for_us": 35,
    "parse_errors": 0,
    "message_type_counts": {
      "offer": 179,
      "offer_revoke": 85
    },
    "revoked_offers_dropped": 71,
    "revokes_invalid_sig": 0
  },
  "offers": [
    {
      "msg_id": "000000006a37726892d8337c20eca9d89871804b9ad2c72f01fea973",
      "timestamp": 1782018664,
      "protocol_version": 4,
      "coin_from": "LTC",
      "coin_to": "WOW",
      "coin_from_id": 3,
      "coin_to_id": 9,
      "amount_from": 15000000000,
      "amount_to": 179067319106422500,
      "amount_from_str": "150.00000000",
      "amount_to_str": "1790673.19106422504",
      "min_bid_amount": 10000000,
      "min_bid_amount_str": "0.10000000",
      "swap_type": 5,
      "lock_type": 2,
      "lock_value": 86400,
      "fee_rate_from": 1000,
      "fee_rate_to": 270000000,
      "amount_negotiable": true,
      "rate_negotiable": false,
      "auto_accept_type": 1,
      "time_valid": 14400,
      "rate": 11937821.2737615,
      "proof_address": "",
      "addr_from": "PoTCAvJLTcgd7LEJk4JkatTY9pGwN78JrA",
      "bid_count": 0,
      "highest_bid": null
    },
    {
      "msg_id": "000000006a37911dff9bf7a97bdc5b3ba4fc9b32d19be07af265d496",
      "timestamp": 1782026525,
      "protocol_version": 4,
      "coin_from": "BTC",
      "coin_to": "XMR",
      "coin_from_id": 2,
      "coin_to_id": 6,
      "amount_from": 1000000,
      "amount_to": 2018515990140,
      "amount_from_str": "0.01000000",
      "amount_to_str": "2.018515990140",
      "min_bid_amount": 100000,
      "min_bid_amount_str": "0.00100000",
      "swap_type": 5,
      "lock_type": 2,
      "lock_value": 86400,
      "fee_rate_from": 2000,
      "fee_rate_to": 20000000,
      "amount_negotiable": true,
      "rate_negotiable": false,
      "auto_accept_type": 1,
      "time_valid": 3900,
      "rate": 2018515.99014,
      "proof_address": "",
      "addr_from": "PmV5sar9m3SbDbgtuC2NZxfRgQ15pwRhXN",
      "bid_count": 0,
      "highest_bid": null
    },
    {
      "msg_id": "000000006a37914f2af77f0bd4cf2ebf5f2b9e4468ce37a5642d0b8b",
      "timestamp": 1782026575,
      "protocol_version": 4,
      "coin_from": "XMR",
      "coin_to": "BCH",
      "coin_from_id": 6,
      "coin_to_id": 17,
      "amount_from": 8091000000000,
      "amount_to": 1370265569,
      "amount_from_str": "8.091000000000",
      "amount_to_str": "13.70265569",
      "min_bid_amount": 1000000000000,
      "min_bid_amount_str": "1.000000000000",
      "swap_type": 5,
      "lock_type": 2,
      "lock_value": 86400,
      "fee_rate_from": 20000000,
      "fee_rate_to": 1000,
      "amount_negotiable": true,
      "rate_negotiable": false,
      "auto_accept_type": 1,
      "time_valid": 1200,
      "rate": 0.00016935676294648375,
      "proof_address": "",
      "addr_from": "PZiiPAUAcMD1yVG41Vns2XXQh8wpe8g8rQ",
      "bid_count": 0,
      "highest_bid": null
    },
    {
      "msg_id": "000000006a37915c347fd1eea2845802a9da06b024f3e7188127a7ba",
      "timestamp": 1782026588,
      "protocol_version": 4,
      "coin_from": "FIRO",
      "coin_to": "LTC",
      "coin_from_id": 13,
      "coin_to_id": 3,
      "amount_from": 34500000000,
      "amount_to": 1107397560,
      "amount_from_str": "345.00000000",
      "amount_to_str": "11.07397560",
      "min_bid_amount": 500000000,
      "min_bid_amount_str": "5.00000000",
      "swap_type": 5,
      "lock_type": 2,
      "lock_value": 86400,
      "fee_rate_from": 1008,
      "fee_rate_to": 1000,
      "amount_negotiable": true,
      "rate_negotiable": false,
      "auto_accept_type": 1,
      "time_valid": 660,
      "rate": 0.03209848,
      "proof_address": "",
      "addr_from": "Pmz4XKbUsrYKKSSoqoqVDYtEnVnH6GEF69",
      "bid_count": 0,
      "highest_bid": null
    },
    {
      "msg_id": "000000006a37918ece445052fab566d2f56585adbe11cb74b8a90fdb",
      "timestamp": 1782026638,
      "protocol_version": 4,
      "coin_from": "LTC",
      "coin_to": "BCH",
      "coin_from_id": 3,
      "coin_to_id": 17,
      "amount_from": 4928000000,
      "amount_to": 1163316049,
      "amount_from_str": "49.28000000",
      "amount_to_str": "11.63316049",
      "min_bid_amount": 500000000,
      "min_bid_amount_str": "5.00000000",
      "swap_type": 5,
      "lock_type": 2,
      "lock_value": 86400,
      "fee_rate_from": 1000,
      "fee_rate_to": 1000,
      "amount_negotiable": true,
      "rate_negotiable": false,
      "auto_accept_type": 1,
      "time_valid": 1200,
      "rate": 0.23606250994318181,
      "proof_address": "",
      "addr_from": "PsCACCLyA1CRe5n8rnoDSKEj2GZmBpu5vH",
      "bid_count": 0,
      "highest_bid": null
    },
    {
      "msg_id": "000000006a37918fc0ece3f0b8e9cbad4cf232574625ff2bd4a9c237",
      "timestamp": 1782026639,
      "protocol_version": 4,
      "coin_from": "WOW",
      "coin_to": "LTC",
      "coin_from_id": 9,
      "coin_to_id": 3,
      "amount_from": 500000000000000,
      "amount_to": 416400000,
      "amount_from_str": "5000.00000000000",
      "amount_to_str": "4.16400000",
      "min_bid_amount": 100000000,
      "min_bid_amount_str": "0.00100000000",
      "swap_type": 5,
      "lock_type": 2,
      "lock_value": 86400,
      "fee_rate_from": 270000000,
      "fee_rate_to": 1000,
      "amount_negotiable": true,
      "rate_negotiable": false,
      "auto_accept_type": 1,
      "time_valid": 3600,
      "rate": 8.328e-07,
      "proof_address": "",
      "addr_from": "PpCGMyrxnGdbdNtstfCiepinbbqJhmhuZe",
      "bid_count": 0,
      "highest_bid": null
    },
    {
      "msg_id": "000000006a3791b0f6c2fa860b6f07bf12a71f9e21b7850295a1bf27",
      "timestamp": 1782026672,
      "protocol_version": 4,
      "coin_from": "XMR",
      "coin_to": "LTC",
      "coin_from_id": 6,
      "coin_to_id": 3,
      "amount_from": 41000000000,
      "amount_to": 30247149,
      "amount_from_str": "0.041000000000",
      "amount_to_str": "0.30247149",
      "min_bid_amount": 10000000000,
      "min_bid_amount_str": "0.010000000000",
      "swap_type": 5,
      "lock_type": 2,
      "lock_value": 86400,
      "fee_rate_from": 20000000,
      "fee_rate_to": 1000,
      "amount_negotiable": true,
      "rate_negotiable": false,
      "auto_accept_type": 1,
      "time_valid": 600,
      "rate": 0.0007377353414634146,
      "proof_address": "",
      "addr_from": "PvcnhYHwjHWoZxDTdpugBfZwzkxHW28iHQ",
      "bid_count": 0,
      "highest_bid": null
    },
    {
      "msg_id": "000000006a3791cc35a5eca3ed1d686370e557ce659fcdb5cd4ad07b",
      "timestamp": 1782026700,
      "protocol_version": 4,
      "coin_from": "LTC",
      "coin_to": "XMR",
      "coin_from_id": 3,
      "coin_to_id": 6,
      "amount_from": 4928000000,
      "amount_to": 7143100203057,
      "amount_from_str": "49.28000000",
      "amount_to_str": "7.143100203057",
      "min_bid_amount": 500000000,
      "min_bid_amount_str": "5.00000000",
      "swap_type": 5,
      "lock_type": 2,
      "lock_value": 86400,
      "fee_rate_from": 1000,
      "fee_rate_to": 20000000,
      "amount_negotiable": true,
      "rate_negotiable": false,
      "auto_accept_type": 1,
      "time_valid": 1200,
      "rate": 1449.4927360099432,
      "proof_address": "",
      "addr_from": "Pd733c6C3eEWt1ySdhusABTUDyTYj1dMw2",
      "bid_count": 0,
      "highest_bid": null
    },
    {
      "msg_id": "000000006a3791e17a9d8a6753a35ad6d046475c214b839c3783f27b",
      "timestamp": 1782026721,
      "protocol_version": 4,
      "coin_from": "BTC",
      "coin_to": "XMR",
      "coin_from_id": 2,
      "coin_to_id": 6,
      "amount_from": 31500000,
      "amount_to": 64314117903929,
      "amount_from_str": "0.31500000",
      "amount_to_str": "64.314117903929",
      "min_bid_amount": 1000000,
      "min_bid_amount_str": "0.01000000",
      "swap_type": 5,
      "lock_type": 2,
      "lock_value": 86400,
      "fee_rate_from": 2000,
      "fee_rate_to": 20000000,
      "amount_negotiable": true,
      "rate_negotiable": false,
      "auto_accept_type": 1,
      "time_valid": 650,
      "rate": 2041718.0286961587,
      "proof_address": "",
      "addr_from": "PjkR6aEbb6pZsJU7cqa6Y6xw1ZR2jU9uSp",
      "bid_count": 0,
      "highest_bid": null
    },
    {
      "msg_id": "000000006a3791f87d8f04045c8643f79c01d92b14bdf4c405691a1c",
      "timestamp": 1782026744,
      "protocol_version": 4,
      "coin_from": "LTC",
      "coin_to": "XMR",
      "coin_from_id": 3,
      "coin_to_id": 6,
      "amount_from": 45000000,
      "amount_to": 63045951297,
      "amount_from_str": "0.45000000",
      "amount_to_str": "0.063045951297",
      "min_bid_amount": 2000000,
      "min_bid_amount_str": "0.02000000",
      "swap_type": 5,
      "lock_type": 2,
      "lock_value": 86400,
      "fee_rate_from": 1000,
      "fee_rate_to": 20000000,
      "amount_negotiable": true,
      "rate_negotiable": false,
      "auto_accept_type": 1,
      "time_valid": 600,
      "rate": 1401.0211399333334,
      "proof_address": "",
      "addr_from": "PpszjhaaTXpBF3xw4XiqRsLp1HuYVjF2ex",
      "bid_count": 0,
      "highest_bid": null
    },
    {
      "msg_id": "000000006a37920e00359c3919dbf98e17b4e212fddd380dc8319ac6",
      "timestamp": 1782026766,
      "protocol_version": 4,
      "coin_from": "XMR",
      "coin_to": "LTC",
      "coin_from_id": 6,
      "coin_to_id": 3,
      "amount_from": 8091000000000,
      "amount_to": 6036279125,
      "amount_from_str": "8.091000000000",
      "amount_to_str": "60.36279125",
      "min_bid_amount": 1000000000000,
      "min_bid_amount_str": "1.000000000000",
      "swap_type": 5,
      "lock_type": 2,
      "lock_value": 86400,
      "fee_rate_from": 20000000,
      "fee_rate_to": 1000,
      "amount_negotiable": true,
      "rate_negotiable": false,
      "auto_accept_type": 1,
      "time_valid": 1200,
      "rate": 0.0007460485879372142,
      "proof_address": "",
      "addr_from": "PkWceERqmSy9PG9a7gdHEXCdBcCYEhdzZa",
      "bid_count": 0,
      "highest_bid": null
    },
    {
      "msg_id": "000000006a379211beb2f2ae29e6afe02e4592cc14472cf920452f6f",
      "timestamp": 1782026769,
      "protocol_version": 4,
      "coin_from": "PART",
      "coin_to": "LTC",
      "coin_from_id": 1,
      "coin_to_id": 3,
      "amount_from": 200000000000,
      "amount_to": 933060000,
      "amount_from_str": "2000.00000000",
      "amount_to_str": "9.33060000",
      "min_bid_amount": 5000000000,
      "min_bid_amount_str": "50.00000000",
      "swap_type": 5,
      "lock_type": 2,
      "lock_value": 86400,
      "fee_rate_from": 200000,
      "fee_rate_to": 1000,
      "amount_negotiable": true,
      "rate_negotiable": false,
      "auto_accept_type": 1,
      "time_valid": 600,
      "rate": 0.0046653,
      "proof_address": "",
      "addr_from": "PuesrBpiJ3Lf6uULcT9LbP9UoJWkQ2JPn2",
      "bid_count": 0,
      "highest_bid": null
    },
    {
      "msg_id": "000000006a379256b03619545d3d662dd430e90cd11267440b5e8d30",
      "timestamp": 1782026838,
      "protocol_version": 4,
      "coin_from": "LTC",
      "coin_to": "BTC",
      "coin_from_id": 3,
      "coin_to_id": 2,
      "amount_from": 4928000000,
      "amount_to": 3572110,
      "amount_from_str": "49.28000000",
      "amount_to_str": "0.03572110",
      "min_bid_amount": 500000000,
      "min_bid_amount_str": "5.00000000",
      "swap_type": 5,
      "lock_type": 2,
      "lock_value": 86400,
      "fee_rate_from": 1000,
      "fee_rate_to": 2126,
      "amount_negotiable": true,
      "rate_negotiable": false,
      "auto_accept_type": 1,
      "time_valid": 1200,
      "rate": 0.0007248599837662337,
      "proof_address": "",
      "addr_from": "PdHwFsfEzJgGLekt6s4bsmv9L4xqqiP45R",
      "bid_count": 0,
      "highest_bid": null
    },
    {
      "msg_id": "000000006a37926f9225d19767da03975ee961504eef24449409a910",
      "timestamp": 1782026863,
      "protocol_version": 4,
      "coin_from": "WOW",
      "coin_to": "PART",
      "coin_from_id": 9,
      "coin_to_id": 1,
      "amount_from": 500000000000000,
      "amount_to": 187435065000,
      "amount_from_str": "5000.00000000000",
      "amount_to_str": "1874.35065000",
      "min_bid_amount": 100000000,
      "min_bid_amount_str": "0.00100000000",
      "swap_type": 5,
      "lock_type": 2,
      "lock_value": 86400,
      "fee_rate_from": 270000000,
      "fee_rate_to": 200000,
      "amount_negotiable": true,
      "rate_negotiable": false,
      "auto_accept_type": 1,
      "time_valid": 3600,
      "rate": 0.00037487013,
      "proof_address": "",
      "addr_from": "Pnzy9GWjWkhbTXAtHZy7HaB2Sz8yta4g26",
      "bid_count": 0,
      "highest_bid": null
    },
    {
      "msg_id": "000000006a3792ace5f66955d2d6094865b814751a8ea403b9f18d38",
      "timestamp": 1782026924,
      "protocol_version": 4,
      "coin_from": "LTC",
      "coin_to": "BCH",
      "coin_from_id": 3,
      "coin_to_id": 17,
      "amount_from": 1300000000,
      "amount_to": 311484485,
      "amount_from_str": "13.00000000",
      "amount_to_str": "3.11484485",
      "min_bid_amount": 100000,
      "min_bid_amount_str": "0.00100000",
      "swap_type": 5,
      "lock_type": 2,
      "lock_value": 86400,
      "fee_rate_from": 1000,
      "fee_rate_to": 1000,
      "amount_negotiable": true,
      "rate_negotiable": false,
      "auto_accept_type": 1,
      "time_valid": 3600,
      "rate": 0.23960345,
      "proof_address": "",
      "addr_from": "PphCp8mpR7GriBGn2QmcrZ9NYrzEQP7WAJ",
      "bid_count": 0,
      "highest_bid": null
    },
    {
      "msg_id": "000000006a3792d74ef9268d295678a01508ea3726ab25addb35755d",
      "timestamp": 1782026967,
      "protocol_version": 4,
      "coin_from": "XMR",
      "coin_to": "BTC",
      "coin_from_id": 6,
      "coin_to_id": 2,
      "amount_from": 500000000000,
      "amount_to": 254976,
      "amount_from_str": "0.500000000000",
      "amount_to_str": "0.00254976",
      "min_bid_amount": 5000000000,
      "min_bid_amount_str": "0.005000000000",
      "swap_type": 5,
      "lock_type": 2,
      "lock_value": 86400,
      "fee_rate_from": 20000000,
      "fee_rate_to": 2125,
      "amount_negotiable": true,
      "rate_negotiable": false,
      "auto_accept_type": 1,
      "time_valid": 3600,
      "rate": 5.09952e-07,
      "proof_address": "",
      "addr_from": "PfwsEoNGHVwDeyyWB3p7yihrMxoEBRMQ2F",
      "bid_count": 0,
      "highest_bid": null
    },
    {
      "msg_id": "000000006a37931d81eb4640aefb770582cbd56ce4963dc22c8cd118",
      "timestamp": 1782027037,
      "protocol_version": 4,
      "coin_from": "XMR",
      "coin_to": "BTC",
      "coin_from_id": 6,
      "coin_to_id": 2,
      "amount_from": 10169000000000,
      "amount_to": 5181268,
      "amount_from_str": "10.169000000000",
      "amount_to_str": "0.05181268",
      "min_bid_amount": 100000000000,
      "min_bid_amount_str": "0.100000000000",
      "swap_type": 5,
      "lock_type": 2,
      "lock_value": 86400,
      "fee_rate_from": 20000000,
      "fee_rate_to": 2000,
      "amount_negotiable": true,
      "rate_negotiable": false,
      "auto_accept_type": 1,
      "time_valid": 900,
      "rate": 5.095159799390304e-07,
      "proof_address": "",
      "addr_from": "PXysnNy8ju5tJ5aWoGnKXi4Xcac79iCZ8H",
      "bid_count": 0,
      "highest_bid": null
    },
    {
      "msg_id": "000000006a37933e4d23dc20b37b8098c9294a5c369b7505d43caec8",
      "timestamp": 1782027070,
      "protocol_version": 4,
      "coin_from": "BTC",
      "coin_to": "XMR",
      "coin_from_id": 2,
      "coin_to_id": 6,
      "amount_from": 1400000,
      "amount_to": 2798771264511,
      "amount_from_str": "0.01400000",
      "amount_to_str": "2.798771264511",
      "min_bid_amount": 500000,
      "min_bid_amount_str": "0.00500000",
      "swap_type": 5,
      "lock_type": 2,
      "lock_value": 86400,
      "fee_rate_from": 2000,
      "fee_rate_to": 20000000,
      "amount_negotiable": true,
      "rate_negotiable": false,
      "auto_accept_type": 1,
      "time_valid": 720,
      "rate": 1999122.3317935714,
      "proof_address": "",
      "addr_from": "PZHkUadDkpp5CKhyo9ZAFBB1pZCCXvM7GY",
      "bid_count": 0,
      "highest_bid": null
    },
    {
      "msg_id": "000000006a3793ab9b0bbe06b69088eba873faab823e622270444942",
      "timestamp": 1782027179,
      "protocol_version": 4,
      "coin_from": "XMR",
      "coin_to": "BTC",
      "coin_from_id": 6,
      "coin_to_id": 2,
      "amount_from": 45000000000000,
      "amount_to": 23288265,
      "amount_from_str": "45.000000000000",
      "amount_to_str": "0.23288265",
      "min_bid_amount": 1000000000000,
      "min_bid_amount_str": "1.000000000000",
      "swap_type": 5,
      "lock_type": 2,
      "lock_value": 86400,
      "fee_rate_from": 20000000,
      "fee_rate_to": 2000,
      "amount_negotiable": true,
      "rate_negotiable": false,
      "auto_accept_type": 1,
      "time_valid": 600,
      "rate": 5.17517e-07,
      "proof_address": "",
      "addr_from": "PqN8aAZUSzUh6ZNZ9gas1TWk8W6FgFC2T7",
      "bid_count": 0,
      "highest_bid": null
    },
    {
      "msg_id": "000000006a3793d2144104a879990fdc7c1e8c3d3416811882bdd6d2",
      "timestamp": 1782027218,
      "protocol_version": 4,
      "coin_from": "PART",
      "coin_to": "XMR",
      "coin_from_id": 1,
      "coin_to_id": 6,
      "amount_from": 200000000000,
      "amount_to": 2000000000000,
      "amount_from_str": "2000.00000000",
      "amount_to_str": "2.000000000000",
      "min_bid_amount": 5000000000,
      "min_bid_amount_str": "50.00000000",
      "swap_type": 5,
      "lock_type": 2,
      "lock_value": 86400,
      "fee_rate_from": 200000,
      "fee_rate_to": 20000000,
      "amount_negotiable": true,
      "rate_negotiable": false,
      "auto_accept_type": 1,
      "time_valid": 600,
      "rate": 10.0,
      "proof_address": "",
      "addr_from": "Po3ZS9kDLBkKKcNwsPic8j6fYMAEpQcrRU",
      "bid_count": 0,
      "highest_bid": null
    },
    {
      "msg_id": "000000006a37940a6cd0d240d11a6a9188abe9048984c65763cbdbb4",
      "timestamp": 1782027274,
      "protocol_version": 4,
      "coin_from": "FIRO",
      "coin_to": "LTC",
      "coin_from_id": 13,
      "coin_to_id": 3,
      "amount_from": 34500000000,
      "amount_to": 1107397560,
      "amount_from_str": "345.00000000",
      "amount_to_str": "11.07397560",
      "min_bid_amount": 500000000,
      "min_bid_amount_str": "5.00000000",
      "swap_type": 5,
      "lock_type": 2,
      "lock_value": 86400,
      "fee_rate_from": 1008,
      "fee_rate_to": 1000,
      "amount_negotiable": true,
      "rate_negotiable": false,
      "auto_accept_type": 1,
      "time_valid": 660,
      "rate": 0.03209848,
      "proof_address": "",
      "addr_from": "Pmz4XKbUsrYKKSSoqoqVDYtEnVnH6GEF69",
      "bid_count": 0,
      "highest_bid": null
    },
    {
      "msg_id": "000000006a37940a39671ef483d30a8380e80ae22a51a0598f08b2b4",
      "timestamp": 1782027274,
      "protocol_version": 4,
      "coin_from": "XMR",
      "coin_to": "BTC",
      "coin_from_id": 6,
      "coin_to_id": 2,
      "amount_from": 10000000000000,
      "amount_to": 5130160,
      "amount_from_str": "10.000000000000",
      "amount_to_str": "0.05130160",
      "min_bid_amount": 5000000000,
      "min_bid_amount_str": "0.005000000000",
      "swap_type": 5,
      "lock_type": 2,
      "lock_value": 86400,
      "fee_rate_from": 20000000,
      "fee_rate_to": 2125,
      "amount_negotiable": true,
      "rate_negotiable": false,
      "auto_accept_type": 1,
      "time_valid": 3600,
      "rate": 5.13016e-07,
      "proof_address": "",
      "addr_from": "PvZLH6n9Wh6uE4QeotHHakMTo3tL8T3B1h",
      "bid_count": 0,
      "highest_bid": null
    },
    {
      "msg_id": "000000006a37946b619351b7014a382099acef515339cf0c4b59b39f",
      "timestamp": 1782027371,
      "protocol_version": 4,
      "coin_from": "LTC",
      "coin_to": "XMR",
      "coin_from_id": 3,
      "coin_to_id": 6,
      "amount_from": 45000000,
      "amount_to": 63088917284,
      "amount_from_str": "0.45000000",
      "amount_to_str": "0.063088917284",
      "min_bid_amount": 2000000,
      "min_bid_amount_str": "0.02000000",
      "swap_type": 5,
      "lock_type": 2,
      "lock_value": 86400,
      "fee_rate_from": 1000,
      "fee_rate_to": 20000000,
      "amount_negotiable": true,
      "rate_negotiable": false,
      "auto_accept_type": 1,
      "time_valid": 600,
      "rate": 1401.9759396444445,
      "proof_address": "",
      "addr_from": "PvSUkUUzgqutAeC1HRt8YGgw96AjwiG3ds",
      "bid_count": 0,
      "highest_bid": null
    },
    {
      "msg_id": "000000006a379497cf66709b96f3d5b1c1335d5b9ec00cb1953d7d74",
      "timestamp": 1782027415,
      "protocol_version": 4,
      "coin_from": "LTC",
      "coin_to": "PART_BLIND",
      "coin_from_id": 3,
      "coin_to_id": 7,
      "amount_from": 270000000,
      "amount_to": 122854415868,
      "amount_from_str": "2.70000000",
      "amount_to_str": "1228.54415868",
      "min_bid_amount": 1000000,
      "min_bid_amount_str": "0.01000000",
      "swap_type": 5,
      "lock_type": 2,
      "lock_value": 86400,
      "fee_rate_from": 1000,
      "fee_rate_to": 200000,
      "amount_negotiable": true,
      "rate_negotiable": false,
      "auto_accept_type": 1,
      "time_valid": 1200,
      "rate": 455.0163550666667,
      "proof_address": "",
      "addr_from": "PdZ7kX1168Kw6uFsWjPMshq88VwDWRiyE6",
      "bid_count": 0,
      "highest_bid": null
    },
    {
      "msg_id": "000000006a3794acb0b00002ea9e0f8872b2c060bad93c5abcc79f9d",
      "timestamp": 1782027436,
      "protocol_version": 4,
      "coin_from": "BTC",
      "coin_to": "XMR",
      "coin_from_id": 2,
      "coin_to_id": 6,
      "amount_from": 31500000,
      "amount_to": 64241968572675,
      "amount_from_str": "0.31500000",
      "amount_to_str": "64.241968572675",
      "min_bid_amount": 1000000,
      "min_bid_amount_str": "0.01000000",
      "swap_type": 5,
      "lock_type": 2,
      "lock_value": 86400,
      "fee_rate_from": 2000,
      "fee_rate_to": 20000000,
      "amount_negotiable": true,
      "rate_negotiable": false,
      "auto_accept_type": 1,
      "time_valid": 650,
      "rate": 2039427.5737357142,
      "proof_address": "",
      "addr_from": "PdLkFKNtBGxSy4Dm4dth8WqTbBKhL1WTjF",
      "bid_count": 0,
      "highest_bid": null
    },
    {
      "msg_id": "000000006a3794ae89d9a70420129d94515199750da8416e0656cbff",
      "timestamp": 1782027438,
      "protocol_version": 4,
      "coin_from": "PART",
      "coin_to": "LTC",
      "coin_from_id": 1,
      "coin_to_id": 3,
      "amount_from": 200000000000,
      "amount_to": 931236000,
      "amount_from_str": "2000.00000000",
      "amount_to_str": "9.31236000",
      "min_bid_amount": 5000000000,
      "min_bid_amount_str": "50.00000000",
      "swap_type": 5,
      "lock_type": 2,
      "lock_value": 86400,
      "fee_rate_from": 200000,
      "fee_rate_to": 1000,
      "amount_negotiable": true,
      "rate_negotiable": false,
      "auto_accept_type": 1,
      "time_valid": 600,
      "rate": 0.00465618,
      "proof_address": "",
      "addr_from": "PmMpYi1AJyLJhsBkn2D8DJvRMT9cUgyv46",
      "bid_count": 0,
      "highest_bid": null
    },
    {
      "msg_id": "000000006a3794c6987951b403ef0fe91f578115733bc39a81880afa",
      "timestamp": 1782027462,
      "protocol_version": 4,
      "coin_from": "XMR",
      "coin_to": "LTC",
      "coin_from_id": 6,
      "coin_to_id": 3,
      "amount_from": 41000000000,
      "amount_to": 30198904,
      "amount_from_str": "0.041000000000",
      "amount_to_str": "0.30198904",
      "min_bid_amount": 10000000000,
      "min_bid_amount_str": "0.010000000000",
      "swap_type": 5,
      "lock_type": 2,
      "lock_value": 86400,
      "fee_rate_from": 20000000,
      "fee_rate_to": 1000,
      "amount_negotiable": true,
      "rate_negotiable": false,
      "auto_accept_type": 1,
      "time_valid": 600,
      "rate": 0.0007365586341463415,
      "proof_address": "",
      "addr_from": "Pj7iGi2BDbx7xtZZSbm5wFYELqpTcoKMWE",
      "bid_count": 0,
      "highest_bid": null
    },
    {
      "msg_id": "000000006a3794ecfdf047c275f8150009bbce0621ba74d982ff21f0",
      "timestamp": 1782027500,
      "protocol_version": 4,
      "coin_from": "WOW",
      "coin_to": "BCH",
      "coin_from_id": 9,
      "coin_to_id": 17,
      "amount_from": 500000000000000,
      "amount_to": 93570000,
      "amount_from_str": "5000.00000000000",
      "amount_to_str": "0.93570000",
      "min_bid_amount": 100000000,
      "min_bid_amount_str": "0.00100000000",
      "swap_type": 5,
      "lock_type": 2,
      "lock_value": 86400,
      "fee_rate_from": 270000000,
      "fee_rate_to": 1000,
      "amount_negotiable": true,
      "rate_negotiable": false,
      "auto_accept_type": 1,
      "time_valid": 3600,
      "rate": 1.8714e-07,
      "proof_address": "",
      "addr_from": "PiK378zg497QeZeqgudyqHq2qboHWgDyRB",
      "bid_count": 0,
      "highest_bid": null
    },
    {
      "msg_id": "000000006a37951eb3150c24e4d43f23704ac13828948da394465482",
      "timestamp": 1782027550,
      "protocol_version": 4,
      "coin_from": "LTC",
      "coin_to": "XMR",
      "coin_from_id": 3,
      "coin_to_id": 6,
      "amount_from": 365000000,
      "amount_to": 512816806447,
      "amount_from_str": "3.65000000",
      "amount_to_str": "0.512816806447",
      "min_bid_amount": 5000000,
      "min_bid_amount_str": "0.05000000",
      "swap_type": 5,
      "lock_type": 2,
      "lock_value": 86400,
      "fee_rate_from": 1000,
      "fee_rate_to": 20000000,
      "amount_negotiable": true,
      "rate_negotiable": false,
      "auto_accept_type": 1,
      "time_valid": 1200,
      "rate": 1404.977551909589,
      "proof_address": "",
      "addr_from": "PrDuVjo2wRefYnv4tw2dsaMqNsE6rKbq2w",
      "bid_count": 0,
      "highest_bid": null
    },
    {
      "msg_id": "000000006a379542c37259332ecbf57e64887a0035f75d5262c66748",
      "timestamp": 1782027586,
      "protocol_version": 4,
      "coin_from": "LTC",
      "coin_to": "XMR",
      "coin_from_id": 3,
      "coin_to_id": 6,
      "amount_from": 1300000000,
      "amount_to": 1831681565142,
      "amount_from_str": "13.00000000",
      "amount_to_str": "1.831681565142",
      "min_bid_amount": 100000,
      "min_bid_amount_str": "0.00100000",
      "swap_type": 5,
      "lock_type": 2,
      "lock_value": 86400,
      "fee_rate_from": 1000,
      "fee_rate_to": 20000000,
      "amount_negotiable": true,
      "rate_negotiable": false,
      "auto_accept_type": 1,
      "time_valid": 3600,
      "rate": 1408.98581934,
      "proof_address": "",
      "addr_from": "PoaTBpgeEHKZhWT3r3eqtfeLFEBVwEwznD",
      "bid_count": 0,
      "highest_bid": null
    },
    {
      "msg_id": "000000006a37958a6923d2f32854d16adef9904336b3b949b61108d7",
      "timestamp": 1782027658,
      "protocol_version": 4,
      "coin_from": "LTC",
      "coin_to": "XMR",
      "coin_from_id": 3,
      "coin_to_id": 6,
      "amount_from": 64000000,
      "amount_to": 89950054400,
      "amount_from_str": "0.64000000",
      "amount_to_str": "0.089950054400",
      "min_bid_amount": 11000000,
      "min_bid_amount_str": "0.11000000",
      "swap_type": 5,
      "lock_type": 2,
      "lock_value": 7200,
      "fee_rate_from": 1000,
      "fee_rate_to": 20000000,
      "amount_negotiable": true,
      "rate_negotiable": false,
      "auto_accept_type": 0,
      "time_valid": 3600,
      "rate": 1405.4696,
      "proof_address": "",
      "addr_from": "PfyGXqmxogLrbidbPoHopfycuG1toZiSBq",
      "bid_count": 0,
      "highest_bid": null
    },
    {
      "msg_id": "000000006a3795940ea4e9ab78c35c2e83dd3e48294aafe5e7d1eba9",
      "timestamp": 1782027668,
      "protocol_version": 4,
      "coin_from": "WOW",
      "coin_to": "LTC",
      "coin_from_id": 9,
      "coin_to_id": 3,
      "amount_from": 133700000000000,
      "amount_to": 117614553,
      "amount_from_str": "1337.00000000000",
      "amount_to_str": "1.17614553",
      "min_bid_amount": 2500000000000,
      "min_bid_amount_str": "25.00000000000",
      "swap_type": 5,
      "lock_type": 2,
      "lock_value": 86400,
      "fee_rate_from": 270000000,
      "fee_rate_to": 1000,
      "amount_negotiable": true,
      "rate_negotiable": false,
      "auto_accept_type": 1,
      "time_valid": 1200,
      "rate": 8.7969e-07,
      "proof_address": "",
      "addr_from": "Pr7ZVRFxFwjM7XHdERRt6CARxf7qeUKhrU",
      "bid_count": 0,
      "highest_bid": null
    },
    {
      "msg_id": "000000006a3795cac8fb0bc50066b1a11057fac7200604433f839c5c",
      "timestamp": 1782027722,
      "protocol_version": 4,
      "coin_from": "XMR",
      "coin_to": "BTC",
      "coin_from_id": 6,
      "coin_to_id": 2,
      "amount_from": 8091000000000,
      "amount_to": 4208023,
      "amount_from_str": "8.091000000000",
      "amount_to_str": "0.04208023",
      "min_bid_amount": 1000000000000,
      "min_bid_amount_str": "1.000000000000",
      "swap_type": 5,
      "lock_type": 2,
      "lock_value": 86400,
      "fee_rate_from": 20000000,
      "fee_rate_to": 2124,
      "amount_negotiable": true,
      "rate_negotiable": false,
      "auto_accept_type": 1,
      "time_valid": 1200,
      "rate": 5.200868866641948e-07,
      "proof_address": "",
      "addr_from": "PejnGfz2VtFk3534h4Fuq4PDD68ebLqzRi",
      "bid_count": 0,
      "highest_bid": null
    },
    {
      "msg_id": "000000006a37960fb95c6578c07c952c7964d73317a02b239259720b",
      "timestamp": 1782027791,
      "protocol_version": 4,
      "coin_from": "BTC",
      "coin_to": "XMR",
      "coin_from_id": 2,
      "coin_to_id": 6,
      "amount_from": 1400000,
      "amount_to": 2797472373540,
      "amount_from_str": "0.01400000",
      "amount_to_str": "2.797472373540",
      "min_bid_amount": 500000,
      "min_bid_amount_str": "0.00500000",
      "swap_type": 5,
      "lock_type": 2,
      "lock_value": 86400,
      "fee_rate_from": 2000,
      "fee_rate_to": 20000000,
      "amount_negotiable": true,
      "rate_negotiable": false,
      "auto_accept_type": 1,
      "time_valid": 720,
      "rate": 1998194.5525285713,
      "proof_address": "",
      "addr_from": "PY8hqquznfJxapsbPNNDtkquaYQs9XFV1Y",
      "bid_count": 0,
      "highest_bid": null
    },
    {
      "msg_id": "000000006a37960fdf6aceeb33ef7afd6fe1938db7ffef1211513ec7",
      "timestamp": 1782027791,
      "protocol_version": 4,
      "coin_from": "XMR",
      "coin_to": "BCH",
      "coin_from_id": 6,
      "coin_to_id": 17,
      "amount_from": 8091000000000,
      "amount_to": 1369607301,
      "amount_from_str": "8.091000000000",
      "amount_to_str": "13.69607301",
      "min_bid_amount": 1000000000000,
      "min_bid_amount_str": "1.000000000000",
      "swap_type": 5,
      "lock_type": 2,
      "lock_value": 86400,
      "fee_rate_from": 20000000,
      "fee_rate_to": 1000,
      "amount_negotiable": true,
      "rate_negotiable": false,
      "auto_accept_type": 1,
      "time_valid": 1200,
      "rate": 0.00016927540489432703,
      "proof_address": "",
      "addr_from": "PqPrJnRW2QLY6WXrrFdsMCHg1hXZM5JiMN",
      "bid_count": 0,
      "highest_bid": null
    },
    {
      "msg_id": "000000006a379633571da4b06c08af99dc2747962e002345a3dbe286",
      "timestamp": 1782027827,
      "protocol_version": 4,
      "coin_from": "XMR",
      "coin_to": "BTC",
      "coin_from_id": 6,
      "coin_to_id": 2,
      "amount_from": 45000000000000,
      "amount_to": 23279850,
      "amount_from_str": "45.000000000000",
      "amount_to_str": "0.23279850",
      "min_bid_amount": 1000000000000,
      "min_bid_amount_str": "1.000000000000",
      "swap_type": 5,
      "lock_type": 2,
      "lock_value": 86400,
      "fee_rate_from": 20000000,
      "fee_rate_to": 2000,
      "amount_negotiable": true,
      "rate_negotiable": false,
      "auto_accept_type": 1,
      "time_valid": 600,
      "rate": 5.1733e-07,
      "proof_address": "",
      "addr_from": "PgQ8WVgymhB2US4UqdaZjfUeyzkSZGTif1",
      "bid_count": 0,
      "highest_bid": null
    },
    {
      "msg_id": "000000006a37964eadccc0b90dbaab1ac1d74ca42d05e950c8492efd",
      "timestamp": 1782027854,
      "protocol_version": 4,
      "coin_from": "LTC",
      "coin_to": "BCH",
      "coin_from_id": 3,
      "coin_to_id": 17,
      "amount_from": 4928000000,
      "amount_to": 1164142129,
      "amount_from_str": "49.28000000",
      "amount_to_str": "11.64142129",
      "min_bid_amount": 500000000,
      "min_bid_amount_str": "5.00000000",
      "swap_type": 5,
      "lock_type": 2,
      "lock_value": 86400,
      "fee_rate_from": 1000,
      "fee_rate_to": 1000,
      "amount_negotiable": true,
      "rate_negotiable": false,
      "auto_accept_type": 1,
      "time_valid": 1200,
      "rate": 0.2362301398133117,
      "proof_address": "",
      "addr_from": "Psh2R78hR5WHwgxyV8K15kmPLgE8W2MFiX",
      "bid_count": 0,
      "highest_bid": null
    },
    {
      "msg_id": "000000006a3796726bbe5d752127b04c594b200723d40d467b6bea76",
      "timestamp": 1782027890,
      "protocol_version": 4,
      "coin_from": "PART",
      "coin_to": "XMR",
      "coin_from_id": 1,
      "coin_to_id": 6,
      "amount_from": 200000000000,
      "amount_to": 2000000000000,
      "amount_from_str": "2000.00000000",
      "amount_to_str": "2.000000000000",
      "min_bid_amount": 5000000000,
      "min_bid_amount_str": "50.00000000",
      "swap_type": 5,
      "lock_type": 2,
      "lock_value": 86400,
      "fee_rate_from": 200000,
      "fee_rate_to": 20000000,
      "amount_negotiable": true,
      "rate_negotiable": false,
      "auto_accept_type": 1,
      "time_valid": 600,
      "rate": 10.0,
      "proof_address": "",
      "addr_from": "Pua2526mMuFkcAXkfxDQY69h9qQ6tLymhR",
      "bid_count": 0,
      "highest_bid": null
    },
    {
      "msg_id": "000000006a37967dde9d6e9bbcc6464106561b57fb953a186780f8c7",
      "timestamp": 1782027901,
      "protocol_version": 4,
      "coin_from": "XMR",
      "coin_to": "BTC",
      "coin_from_id": 6,
      "coin_to_id": 2,
      "amount_from": 5000000000000,
      "amount_to": 2563175,
      "amount_from_str": "5.000000000000",
      "amount_to_str": "0.02563175",
      "min_bid_amount": 5000000000,
      "min_bid_amount_str": "0.005000000000",
      "swap_type": 5,
      "lock_type": 2,
      "lock_value": 86400,
      "fee_rate_from": 20000000,
      "fee_rate_to": 2124,
      "amount_negotiable": true,
      "rate_negotiable": false,
      "auto_accept_type": 1,
      "time_valid": 3600,
      "rate": 5.12635e-07,
      "proof_address": "",
      "addr_from": "PtcUV16AYfHLarnV7BvxKk2eU4G6EqBc9t",
      "bid_count": 0,
      "highest_bid": null
    },
    {
      "msg_id": "000000006a379697775c04d9bc2cce331a5f8c3ea7cdce82a3bdf6e9",
      "timestamp": 1782027927,
      "protocol_version": 4,
      "coin_from": "LTC",
      "coin_to": "XMR",
      "coin_from_id": 3,
      "coin_to_id": 6,
      "amount_from": 4928000000,
      "amount_to": 7151608265253,
      "amount_from_str": "49.28000000",
      "amount_to_str": "7.151608265253",
      "min_bid_amount": 500000000,
      "min_bid_amount_str": "5.00000000",
      "swap_type": 5,
      "lock_type": 2,
      "lock_value": 86400,
      "fee_rate_from": 1000,
      "fee_rate_to": 20000000,
      "amount_negotiable": true,
      "rate_negotiable": false,
      "auto_accept_type": 1,
      "time_valid": 1200,
      "rate": 1451.2192096698457,
      "proof_address": "",
      "addr_from": "PYp5btM8jiBjJ4dSoXn2wEzDdAmkWRNQY2",
      "bid_count": 0,
      "highest_bid": null
    },
    {
      "msg_id": "000000006a3796b8a5bb50d3161a9a7d20877a687a714f1c16b19f86",
      "timestamp": 1782027960,
      "protocol_version": 4,
      "coin_from": "FIRO",
      "coin_to": "LTC",
      "coin_from_id": 13,
      "coin_to_id": 3,
      "amount_from": 34500000000,
      "amount_to": 1107397560,
      "amount_from_str": "345.00000000",
      "amount_to_str": "11.07397560",
      "min_bid_amount": 500000000,
      "min_bid_amount_str": "5.00000000",
      "swap_type": 5,
      "lock_type": 2,
      "lock_value": 86400,
      "fee_rate_from": 1009,
      "fee_rate_to": 1000,
      "amount_negotiable": true,
      "rate_negotiable": false,
      "auto_accept_type": 1,
      "time_valid": 660,
      "rate": 0.03209848,
      "proof_address": "",
      "addr_from": "Pmz4XKbUsrYKKSSoqoqVDYtEnVnH6GEF69",
      "bid_count": 0,
      "highest_bid": null
    },
    {
      "msg_id": "000000006a3796cc5d638981350189ea675035bee7a0299431ef9765",
      "timestamp": 1782027980,
      "protocol_version": 4,
      "coin_from": "XMR",
      "coin_to": "BTC",
      "coin_from_id": 6,
      "coin_to_id": 2,
      "amount_from": 10169000000000,
      "amount_to": 5179407,
      "amount_from_str": "10.169000000000",
      "amount_to_str": "0.05179407",
      "min_bid_amount": 100000000000,
      "min_bid_amount_str": "0.100000000000",
      "swap_type": 5,
      "lock_type": 2,
      "lock_value": 86400,
      "fee_rate_from": 20000000,
      "fee_rate_to": 2000,
      "amount_negotiable": true,
      "rate_negotiable": false,
      "auto_accept_type": 1,
      "time_valid": 900,
      "rate": 5.0933297276035e-07,
      "proof_address": "",
      "addr_from": "PoGGWe89wT5HcTLj3jbtyqySgqfKFYpFKc",
      "bid_count": 0,
      "highest_bid": null
    },
    {
      "msg_id": "000000006a3796d8baecc08b565c7538e1d0812bbbb03597b8f8ba7c",
      "timestamp": 1782027992,
      "protocol_version": 4,
      "coin_from": "XMR",
      "coin_to": "LTC",
      "coin_from_id": 6,
      "coin_to_id": 3,
      "amount_from": 8091000000000,
      "amount_to": 6020367332,
      "amount_from_str": "8.091000000000",
      "amount_to_str": "60.20367332",
      "min_bid_amount": 1000000000000,
      "min_bid_amount_str": "1.000000000000",
      "swap_type": 5,
      "lock_type": 2,
      "lock_value": 86400,
      "fee_rate_from": 20000000,
      "fee_rate_to": 1000,
      "amount_negotiable": true,
      "rate_negotiable": false,
      "auto_accept_type": 1,
      "time_valid": 1200,
      "rate": 0.0007440819839327648,
      "proof_address": "",
      "addr_from": "PrREYuR3ghjgnT7hDM4GmwDuTzpM9ZH78G",
      "bid_count": 0,
      "highest_bid": null
    },
    {
      "msg_id": "000000006a37970df1ce18619a12c7470ea70b69d77c2d19e93abb89",
      "timestamp": 1782028045,
      "protocol_version": 4,
      "coin_from": "LTC",
      "coin_to": "XMR",
      "coin_from_id": 3,
      "coin_to_id": 6,
      "amount_from": 45000000,
      "amount_to": 63143009663,
      "amount_from_str": "0.45000000",
      "amount_to_str": "0.063143009663",
      "min_bid_amount": 2000000,
      "min_bid_amount_str": "0.02000000",
      "swap_type": 5,
      "lock_type": 2,
      "lock_value": 86400,
      "fee_rate_from": 1000,
      "fee_rate_to": 20000000,
      "amount_negotiable": true,
      "rate_negotiable": false,
      "auto_accept_type": 1,
      "time_valid": 600,
      "rate": 1403.1779925111111,
      "proof_address": "",
      "addr_from": "PqQ3GfPUfuS3zvAwNDbg4SdcJbMcPjKzbN",
      "bid_count": 0,
      "highest_bid": null
    },
    {
      "msg_id": "000000006a379719924abd7cb8e08d851eb49b99ab0f3fc087be54b6",
      "timestamp": 1782028057,
      "protocol_version": 4,
      "coin_from": "LTC",
      "coin_to": "BTC",
      "coin_from_id": 3,
      "coin_to_id": 2,
      "amount_from": 4928000000,
      "amount_to": 3578861,
      "amount_from_str": "49.28000000",
      "amount_to_str": "0.03578861",
      "min_bid_amount": 500000000,
      "min_bid_amount_str": "5.00000000",
      "swap_type": 5,
      "lock_type": 2,
      "lock_value": 86400,
      "fee_rate_from": 1000,
      "fee_rate_to": 2124,
      "amount_negotiable": true,
      "rate_negotiable": false,
      "auto_accept_type": 1,
      "time_valid": 1200,
      "rate": 0.0007262299107142857,
      "proof_address": "",
      "addr_from": "Pj2Q2WJPfKEWvfESbdTRZpSTpSPRHXVfzr",
      "bid_count": 0,
      "highest_bid": null
    },
    {
      "msg_id": "000000006a37974f3d0aa2aaf7204451f0fb5a56c90cfaf6a5931269",
      "timestamp": 1782028111,
      "protocol_version": 4,
      "coin_from": "BTC",
      "coin_to": "XMR",
      "coin_from_id": 2,
      "coin_to_id": 6,
      "amount_from": 10000000,
      "amount_to": 20111910925365,
      "amount_from_str": "0.10000000",
      "amount_to_str": "20.111910925365",
      "min_bid_amount": 100000,
      "min_bid_amount_str": "0.00100000",
      "swap_type": 5,
      "lock_type": 2,
      "lock_value": 86400,
      "fee_rate_from": 2124,
      "fee_rate_to": 20000000,
      "amount_negotiable": true,
      "rate_negotiable": false,
      "auto_accept_type": 1,
      "time_valid": 3600,
      "rate": 2011191.0925365,
      "proof_address": "",
      "addr_from": "Ph6oSRM1j63aQwaBue48iuNcvj5UkMwnsG",
      "bid_count": 0,
      "highest_bid": null
    },
    {
      "msg_id": "000000006a37975bb03567eff05acb03e7de56caf220999e38972444",
      "timestamp": 1782028123,
      "protocol_version": 4,
      "coin_from": "XMR",
      "coin_to": "LTC",
      "coin_from_id": 6,
      "coin_to_id": 3,
      "amount_from": 41000000000,
      "amount_to": 30173034,
      "amount_from_str": "0.041000000000",
      "amount_to_str": "0.30173034",
      "min_bid_amount": 10000000000,
      "min_bid_amount_str": "0.010000000000",
      "swap_type": 5,
      "lock_type": 2,
      "lock_value": 86400,
      "fee_rate_from": 20000000,
      "fee_rate_to": 1000,
      "amount_negotiable": true,
      "rate_negotiable": false,
      "auto_accept_type": 1,
      "time_valid": 600,
      "rate": 0.0007359276585365853,
      "proof_address": "",
      "addr_from": "PYqtJt83oWxWYsSxhR6Vu6sB3iXnTxSSwF",
      "bid_count": 0,
      "highest_bid": null
    },
    {
      "msg_id": "000000006a37976bb02cb79b2f5165384504a5a7602789e288407553",
      "timestamp": 1782028139,
      "protocol_version": 4,
      "coin_from": "XMR",
      "coin_to": "LTC",
      "coin_from_id": 6,
      "coin_to_id": 3,
      "amount_from": 1000000000000,
      "amount_to": 744153537,
      "amount_from_str": "1.000000000000",
      "amount_to_str": "7.44153537",
      "min_bid_amount": 500000000000,
      "min_bid_amount_str": "0.500000000000",
      "swap_type": 5,
      "lock_type": 2,
      "lock_value": 86400,
      "fee_rate_from": 20000000,
      "fee_rate_to": 1000,
      "amount_negotiable": true,
      "rate_negotiable": false,
      "auto_accept_type": 1,
      "time_valid": 3600,
      "rate": 0.000744153537,
      "proof_address": "",
      "addr_from": "PveTb8wpSfLQiDsGxjdk1i8RqFBfqs1Pdx",
      "bid_count": 0,
      "highest_bid": null
    },
    {
      "msg_id": "000000006a379777550d9d0cf2b31ffb1d0a58927fbf0609fb5de63e",
      "timestamp": 1782028151,
      "protocol_version": 4,
      "coin_from": "BTC",
      "coin_to": "XMR",
      "coin_from_id": 2,
      "coin_to_id": 6,
      "amount_from": 31500000,
      "amount_to": 64307107028106,
      "amount_from_str": "0.31500000",
      "amount_to_str": "64.307107028106",
      "min_bid_amount": 1000000,
      "min_bid_amount_str": "0.01000000",
      "swap_type": 5,
      "lock_type": 2,
      "lock_value": 86400,
      "fee_rate_from": 2000,
      "fee_rate_to": 20000000,
      "amount_negotiable": true,
      "rate_negotiable": false,
      "auto_accept_type": 1,
      "time_valid": 650,
      "rate": 2041495.4612097142,
      "proof_address": "",
      "addr_from": "PqVeFLthGtp6WVErjCFDBTiLTgJjxn1zHU",
      "bid_count": 0,
      "highest_bid": null
    },
    {
      "msg_id": "000000006a3797840f92634fa8916f019bd2c7403a3ee7b8506b76ff",
      "timestamp": 1782028164,
      "protocol_version": 4,
      "coin_from": "PART",
      "coin_to": "LTC",
      "coin_from_id": 1,
      "coin_to_id": 3,
      "amount_from": 200000000000,
      "amount_to": 930844000,
      "amount_from_str": "2000.00000000",
      "amount_to_str": "9.30844000",
      "min_bid_amount": 5000000000,
      "min_bid_amount_str": "50.00000000",
      "swap_type": 5,
      "lock_type": 2,
      "lock_value": 86400,
      "fee_rate_from": 200000,
      "fee_rate_to": 1000,
      "amount_negotiable": true,
      "rate_negotiable": false,
      "auto_accept_type": 1,
      "time_valid": 600,
      "rate": 0.00465422,
      "proof_address": "",
      "addr_from": "PZ4awsZHnRfxTN3Z2LCEBtXzueoWchZ2bK",
      "bid_count": 0,
      "highest_bid": null
    },
    {
      "msg_id": "000000006a3798640871a8fdd141353c2bde0ee2bab70b11fa066004",
      "timestamp": 1782028388,
      "protocol_version": 4,
      "coin_from": "XMR",
      "coin_to": "BTC",
      "coin_from_id": 6,
      "coin_to_id": 2,
      "amount_from": 2000000000000,
      "amount_to": 1031638,
      "amount_from_str": "2.000000000000",
      "amount_to_str": "0.01031638",
      "min_bid_amount": 5000000000,
      "min_bid_amount_str": "0.005000000000",
      "swap_type": 5,
      "lock_type": 2,
      "lock_value": 86400,
      "fee_rate_from": 20000000,
      "fee_rate_to": 2124,
      "amount_negotiable": true,
      "rate_negotiable": false,
      "auto_accept_type": 1,
      "time_valid": 3600,
      "rate": 5.15819e-07,
      "proof_address": "",
      "addr_from": "Pt1SnNdWCQmEX76tq8VcB7HDqKTiCQt1Pj",
      "bid_count": 0,
      "highest_bid": null
    },
    {
      "msg_id": "000000006a3798c3a4af56226b77970223272ae5e25638b03c20b7b3",
      "timestamp": 1782028483,
      "protocol_version": 4,
      "coin_from": "XMR",
      "coin_to": "BTC",
      "coin_from_id": 6,
      "coin_to_id": 2,
      "amount_from": 45000000000000,
      "amount_to": 23362605,
      "amount_from_str": "45.000000000000",
      "amount_to_str": "0.23362605",
      "min_bid_amount": 1000000000000,
      "min_bid_amount_str": "1.000000000000",
      "swap_type": 5,
      "lock_type": 2,
      "lock_value": 86400,
      "fee_rate_from": 20000000,
      "fee_rate_to": 2000,
      "amount_negotiable": true,
      "rate_negotiable": false,
      "auto_accept_type": 1,
      "time_valid": 600,
      "rate": 5.19169e-07,
      "proof_address": "",
      "addr_from": "PbrzFHjGX4uviKuPhXLYFj4EE8jBrM9VVG",
      "bid_count": 0,
      "highest_bid": null
    },
    {
      "msg_id": "000000006a3798e0cecc57e3028076d2c8c114cb4df6b3c015ae2e12",
      "timestamp": 1782028512,
      "protocol_version": 4,
      "coin_from": "BTC",
      "coin_to": "XMR",
      "coin_from_id": 2,
      "coin_to_id": 6,
      "amount_from": 1400000,
      "amount_to": 2797472373540,
      "amount_from_str": "0.01400000",
      "amount_to_str": "2.797472373540",
      "min_bid_amount": 500000,
      "min_bid_amount_str": "0.00500000",
      "swap_type": 5,
      "lock_type": 2,
      "lock_value": 86400,
      "fee_rate_from": 2000,
      "fee_rate_to": 20000000,
      "amount_negotiable": true,
      "rate_negotiable": false,
      "auto_accept_type": 1,
      "time_valid": 720,
      "rate": 1998194.5525285713,
      "proof_address": "",
      "addr_from": "Pting4y5hX9VD3NdoW5dek7U7WHVayDwk6",
      "bid_count": 0,
      "highest_bid": null
    },
    {
      "msg_id": "000000006a3799027efd54942d6c4fbe215e4de4ef3ddf47887505e8",
      "timestamp": 1782028546,
      "protocol_version": 4,
      "coin_from": "PART",
      "coin_to": "XMR",
      "coin_from_id": 1,
      "coin_to_id": 6,
      "amount_from": 200000000000,
      "amount_to": 2000000000000,
      "amount_from_str": "2000.00000000",
      "amount_to_str": "2.000000000000",
      "min_bid_amount": 5000000000,
      "min_bid_amount_str": "50.00000000",
      "swap_type": 5,
      "lock_type": 2,
      "lock_value": 86400,
      "fee_rate_from": 200000,
      "fee_rate_to": 20000000,
      "amount_negotiable": true,
      "rate_negotiable": false,
      "auto_accept_type": 1,
      "time_valid": 600,
      "rate": 10.0,
      "proof_address": "",
      "addr_from": "PmEYV8DD2dxM6D6QnnRFMjFzX21nYadM5R",
      "bid_count": 0,
      "highest_bid": null
    },
    {
      "msg_id": "000000006a37996695ee3bdc9d54b773567c48fb10b60ef87524d331",
      "timestamp": 1782028646,
      "protocol_version": 4,
      "coin_from": "LTC",
      "coin_to": "PART_BLIND",
      "coin_from_id": 3,
      "coin_to_id": 7,
      "amount_from": 270000000,
      "amount_to": 122959837355,
      "amount_from_str": "2.70000000",
      "amount_to_str": "1229.59837355",
      "min_bid_amount": 1000000,
      "min_bid_amount_str": "0.01000000",
      "swap_type": 5,
      "lock_type": 2,
      "lock_value": 86400,
      "fee_rate_from": 1000,
      "fee_rate_to": 200000,
      "amount_negotiable": true,
      "rate_negotiable": false,
      "auto_accept_type": 1,
      "time_valid": 1200,
      "rate": 455.4068050185185,
      "proof_address": "",
      "addr_from": "PdZ7kX1168Kw6uFsWjPMshq88VwDWRiyE6",
      "bid_count": 0,
      "highest_bid": null
    },
    {
      "msg_id": "000000006a37998921e724011e9c82c4dcb405efbb2ed95a265b4d2f",
      "timestamp": 1782028681,
      "protocol_version": 4,
      "coin_from": "LTC",
      "coin_to": "XMR",
      "coin_from_id": 3,
      "coin_to_id": 6,
      "amount_from": 45000000,
      "amount_to": 62931511104,
      "amount_from_str": "0.45000000",
      "amount_to_str": "0.062931511104",
      "min_bid_amount": 2000000,
      "min_bid_amount_str": "0.02000000",
      "swap_type": 5,
      "lock_type": 2,
      "lock_value": 86400,
      "fee_rate_from": 1000,
      "fee_rate_to": 20000000,
      "amount_negotiable": true,
      "rate_negotiable": false,
      "auto_accept_type": 1,
      "time_valid": 600,
      "rate": 1398.4780245333334,
      "proof_address": "",
      "addr_from": "PiSzN8iW2u1wqy39yE2gVBiyoQWaw9tS5Q",
      "bid_count": 0,
      "highest_bid": null
    },
    {
      "msg_id": "000000006a3799a0d99923883ba631840f024ca5b4ead37d69f62983",
      "timestamp": 1782028704,
      "protocol_version": 4,
      "coin_from": "FIRO",
      "coin_to": "LTC",
      "coin_from_id": 13,
      "coin_to_id": 3,
      "amount_from": 34500000000,
      "amount_to": 1107397560,
      "amount_from_str": "345.00000000",
      "amount_to_str": "11.07397560",
      "min_bid_amount": 500000000,
      "min_bid_amount_str": "5.00000000",
      "swap_type": 5,
      "lock_type": 2,
      "lock_value": 86400,
      "fee_rate_from": 1010,
      "fee_rate_to": 1000,
      "amount_negotiable": true,
      "rate_negotiable": false,
      "auto_accept_type": 1,
      "time_valid": 660,
      "rate": 0.03209848,
      "proof_address": "",
      "addr_from": "Pmz4XKbUsrYKKSSoqoqVDYtEnVnH6GEF69",
      "bid_count": 0,
      "highest_bid": null
    },
    {
      "msg_id": "000000006a3799dd1859896429b77338254c68eb3c4310f6ef6f4eb4",
      "timestamp": 1782028765,
      "protocol_version": 4,
      "coin_from": "WOW",
      "coin_to": "BCH",
      "coin_from_id": 9,
      "coin_to_id": 17,
      "amount_from": 1000000000000000,
      "amount_to": 93700000,
      "amount_from_str": "10000.00000000000",
      "amount_to_str": "0.93700000",
      "min_bid_amount": 500000000000000,
      "min_bid_amount_str": "5000.00000000000",
      "swap_type": 5,
      "lock_type": 2,
      "lock_value": 86400,
      "fee_rate_from": 270000000,
      "fee_rate_to": 1000,
      "amount_negotiable": true,
      "rate_negotiable": false,
      "auto_accept_type": 1,
      "time_valid": 14400,
      "rate": 9.37e-08,
      "proof_address": "",
      "addr_from": "PdEj8ugWSRhoZ8UC877EbBUSbEtjSyedBB",
      "bid_count": 0,
      "highest_bid": null
    },
    {
      "msg_id": "000000006a3799df99819b8c652dcf1efee45f1d0f167f1ade936022",
      "timestamp": 1782028767,
      "protocol_version": 4,
      "coin_from": "LTC",
      "coin_to": "XMR",
      "coin_from_id": 3,
      "coin_to_id": 6,
      "amount_from": 365000000,
      "amount_to": 510242899231,
      "amount_from_str": "3.65000000",
      "amount_to_str": "0.510242899231",
      "min_bid_amount": 5000000,
      "min_bid_amount_str": "0.05000000",
      "swap_type": 5,
      "lock_type": 2,
      "lock_value": 86400,
      "fee_rate_from": 1000,
      "fee_rate_to": 20000000,
      "amount_negotiable": true,
      "rate_negotiable": false,
      "auto_accept_type": 1,
      "time_valid": 1200,
      "rate": 1397.9257513178081,
      "proof_address": "",
      "addr_from": "PrDuVjo2wRefYnv4tw2dsaMqNsE6rKbq2w",
      "bid_count": 0,
      "highest_bid": null
    },
    {
      "msg_id": "000000006a379a0bf6e0bbffdfb3cc9c1ea96b5676aa95a3ec9d2ec7",
      "timestamp": 1782028811,
      "protocol_version": 4,
      "coin_from": "BTC",
      "coin_to": "XMR",
      "coin_from_id": 2,
      "coin_to_id": 6,
      "amount_from": 470000,
      "amount_to": 999859200000,
      "amount_from_str": "0.00470000",
      "amount_to_str": "0.999859200000",
      "min_bid_amount": 470000,
      "min_bid_amount_str": "0.00470000",
      "swap_type": 5,
      "lock_type": 2,
      "lock_value": 86400,
      "fee_rate_from": 2124,
      "fee_rate_to": 20000000,
      "amount_negotiable": true,
      "rate_negotiable": false,
      "auto_accept_type": 1,
      "time_valid": 3600,
      "rate": 2127360.0,
      "proof_address": "",
      "addr_from": "Pa3iz6DPtsrYURqbSgCiL4Sm8vM5TcFZPq",
      "bid_count": 0,
      "highest_bid": null
    },
    {
      "msg_id": "000000006a379a1a5b5dfe5d22bd034a735d2a07b8436145d4a4f1b5",
      "timestamp": 1782028826,
      "protocol_version": 4,
      "coin_from": "PART",
      "coin_to": "LTC",
      "coin_from_id": 1,
      "coin_to_id": 3,
      "amount_from": 200000000000,
      "amount_to": 931264000,
      "amount_from_str": "2000.00000000",
      "amount_to_str": "9.31264000",
      "min_bid_amount": 5000000000,
      "min_bid_amount_str": "50.00000000",
      "swap_type": 5,
      "lock_type": 2,
      "lock_value": 86400,
      "fee_rate_from": 200000,
      "fee_rate_to": 1000,
      "amount_negotiable": true,
      "rate_negotiable": false,
      "auto_accept_type": 1,
      "time_valid": 600,
      "rate": 0.00465632,
      "proof_address": "",
      "addr_from": "PnQR2o3K88aW8uU5iibyZBDFBLZUcrLuYK",
      "bid_count": 0,
      "highest_bid": null
    },
    {
      "msg_id": "000000006a379a3f36b0ceb27535b6b37465b89abd871ae21268a709",
      "timestamp": 1782028863,
      "protocol_version": 4,
      "coin_from": "BTC",
      "coin_to": "XMR",
      "coin_from_id": 2,
      "coin_to_id": 6,
      "amount_from": 31500000,
      "amount_to": 63883324752659,
      "amount_from_str": "0.31500000",
      "amount_to_str": "63.883324752659",
      "min_bid_amount": 1000000,
      "min_bid_amount_str": "0.01000000",
      "swap_type": 5,
      "lock_type": 2,
      "lock_value": 86400,
      "fee_rate_from": 2000,
      "fee_rate_to": 20000000,
      "amount_negotiable": true,
      "rate_negotiable": false,
      "auto_accept_type": 1,
      "time_valid": 650,
      "rate": 2028042.0556399683,
      "proof_address": "",
      "addr_from": "PYuakhAQkaBCXhZppdo1ee45xKaNg2yVmo",
      "bid_count": 0,
      "highest_bid": null
    },
    {
      "msg_id": "000000006a379a74f6d04096fe84a93c3b6de92875d2ef9cf96405f7",
      "timestamp": 1782028916,
      "protocol_version": 4,
      "coin_from": "WOW",
      "coin_to": "LTC",
      "coin_from_id": 9,
      "coin_to_id": 3,
      "amount_from": 133700000000000,
      "amount_to": 117614553,
      "amount_from_str": "1337.00000000000",
      "amount_to_str": "1.17614553",
      "min_bid_amount": 2500000000000,
      "min_bid_amount_str": "25.00000000000",
      "swap_type": 5,
      "lock_type": 2,
      "lock_value": 86400,
      "fee_rate_from": 270000000,
      "fee_rate_to": 1000,
      "amount_negotiable": true,
      "rate_negotiable": false,
      "auto_accept_type": 1,
      "time_valid": 1200,
      "rate": 8.7969e-07,
      "proof_address": "",
      "addr_from": "Pu1RDRJ2pGaxGMCZPooEneDYTR6gTbAmf5",
      "bid_count": 0,
      "highest_bid": null
    },
    {
      "msg_id": "000000006a379a81444ab3fb1d079b1b4d1ac9984ca798217829e7cf",
      "timestamp": 1782028929,
      "protocol_version": 4,
      "coin_from": "XMR",
      "coin_to": "BTC",
      "coin_from_id": 6,
      "coin_to_id": 2,
      "amount_from": 10169000000000,
      "amount_to": 5206650,
      "amount_from_str": "10.169000000000",
      "amount_to_str": "0.05206650",
      "min_bid_amount": 100000000000,
      "min_bid_amount_str": "0.100000000000",
      "swap_type": 5,
      "lock_type": 2,
      "lock_value": 86400,
      "fee_rate_from": 20000000,
      "fee_rate_to": 2000,
      "amount_negotiable": true,
      "rate_negotiable": false,
      "auto_accept_type": 1,
      "time_valid": 900,
      "rate": 5.120119972465336e-07,
      "proof_address": "",
      "addr_from": "PvGk3HvCYLr9kDeJnoUrSTqjUbfV4vRzYn",
      "bid_count": 0,
      "highest_bid": null
    },
    {
      "msg_id": "000000006a379a8b876a12dd3b077abf60410571fa99320cc6aae353",
      "timestamp": 1782028939,
      "protocol_version": 4,
      "coin_from": "XMR",
      "coin_to": "BTC",
      "coin_from_id": 6,
      "coin_to_id": 2,
      "amount_from": 8091000000000,
      "amount_to": 4226859,
      "amount_from_str": "8.091000000000",
      "amount_to_str": "0.04226859",
      "min_bid_amount": 1000000000000,
      "min_bid_amount_str": "1.000000000000",
      "swap_type": 5,
      "lock_type": 2,
      "lock_value": 86400,
      "fee_rate_from": 20000000,
      "fee_rate_to": 2124,
      "amount_negotiable": true,
      "rate_negotiable": false,
      "auto_accept_type": 1,
      "time_valid": 1200,
      "rate": 5.224149054505005e-07,
      "proof_address": "",
      "addr_from": "PvuN9QFg1b31cfNqJ4zrb9sUyB5cdsH4kM",
      "bid_count": 0,
      "highest_bid": null
    },
    {
      "msg_id": "000000006a379ad1aa36ff067f5450d4d6c76fd43e3b0d86fa340ebd",
      "timestamp": 1782029009,
      "protocol_version": 4,
      "coin_from": "XMR",
      "coin_to": "BCH",
      "coin_from_id": 6,
      "coin_to_id": 17,
      "amount_from": 8091000000000,
      "amount_to": 1377199718,
      "amount_from_str": "8.091000000000",
      "amount_to_str": "13.77199718",
      "min_bid_amount": 1000000000000,
      "min_bid_amount_str": "1.000000000000",
      "swap_type": 5,
      "lock_type": 2,
      "lock_value": 86400,
      "fee_rate_from": 20000000,
      "fee_rate_to": 1000,
      "amount_negotiable": true,
      "rate_negotiable": false,
      "auto_accept_type": 1,
      "time_valid": 1200,
      "rate": 0.00017021378296873068,
      "proof_address": "",
      "addr_from": "PdiWRcLZ2x9guK7HQBagh2FtNQ9UuzctWK",
      "bid_count": 0,
      "highest_bid": null
    },
    {
      "msg_id": "000000006a379b17a3ef2be276340678bda8d3daf84c5f9fd82715ae",
      "timestamp": 1782029079,
      "protocol_version": 4,
      "coin_from": "LTC",
      "coin_to": "BCH",
      "coin_from_id": 3,
      "coin_to_id": 17,
      "amount_from": 4928000000,
      "amount_to": 1166016938,
      "amount_from_str": "49.28000000",
      "amount_to_str": "11.66016938",
      "min_bid_amount": 500000000,
      "min_bid_amount_str": "5.00000000",
      "swap_type": 5,
      "lock_type": 2,
      "lock_value": 86400,
      "fee_rate_from": 1000,
      "fee_rate_to": 1000,
      "amount_negotiable": true,
      "rate_negotiable": false,
      "auto_accept_type": 1,
      "time_valid": 1200,
      "rate": 0.2366105799512987,
      "proof_address": "",
      "addr_from": "ParfCpKSqtk2TZiiJ9eYhKQRsGF4x8EZKq",
      "bid_count": 0,
      "highest_bid": null
    },
    {
      "msg_id": "000000006a379b4dc2a31c664a562cb247063b2dee7fb23d5d1cca54",
      "timestamp": 1782029133,
      "protocol_version": 4,
      "coin_from": "XMR",
      "coin_to": "BTC",
      "coin_from_id": 6,
      "coin_to_id": 2,
      "amount_from": 45000000000000,
      "amount_to": 23424390,
      "amount_from_str": "45.000000000000",
      "amount_to_str": "0.23424390",
      "min_bid_amount": 1000000000000,
      "min_bid_amount_str": "1.000000000000",
      "swap_type": 5,
      "lock_type": 2,
      "lock_value": 86400,
      "fee_rate_from": 20000000,
      "fee_rate_to": 2000,
      "amount_negotiable": true,
      "rate_negotiable": false,
      "auto_accept_type": 1,
      "time_valid": 600,
      "rate": 5.20542e-07,
      "proof_address": "",
      "addr_from": "PZnKSPdLBVKqCwbaNgJ4Hi7Po72PdT51hh",
      "bid_count": 0,
      "highest_bid": null
    },
    {
      "msg_id": "000000006a379b5d4b56e3417f2a1e8fac2c8bcea2777efc45626607",
      "timestamp": 1782029149,
      "protocol_version": 4,
      "coin_from": "LTC",
      "coin_to": "XMR",
      "coin_from_id": 3,
      "coin_to_id": 6,
      "amount_from": 4928000000,
      "amount_to": 7123635873101,
      "amount_from_str": "49.28000000",
      "amount_to_str": "7.123635873101",
      "min_bid_amount": 500000000,
      "min_bid_amount_str": "5.00000000",
      "swap_type": 5,
      "lock_type": 2,
      "lock_value": 86400,
      "fee_rate_from": 1000,
      "fee_rate_to": 20000000,
      "amount_negotiable": true,
      "rate_negotiable": false,
      "auto_accept_type": 1,
      "time_valid": 1200,
      "rate": 1445.5429937299107,
      "proof_address": "",
      "addr_from": "PoP7K5TpoDDqG8zTYrRsh5fi182ss4UrK3",
      "bid_count": 0,
      "highest_bid": null
    },
    {
      "msg_id": "000000006a379b9e1fa2b0dc345f94f8a99f796af146d0f4be05f9d5",
      "timestamp": 1782029214,
      "protocol_version": 4,
      "coin_from": "XMR",
      "coin_to": "LTC",
      "coin_from_id": 6,
      "coin_to_id": 3,
      "amount_from": 8091000000000,
      "amount_to": 6058935066,
      "amount_from_str": "8.091000000000",
      "amount_to_str": "60.58935066",
      "min_bid_amount": 1000000000000,
      "min_bid_amount_str": "1.000000000000",
      "swap_type": 5,
      "lock_type": 2,
      "lock_value": 86400,
      "fee_rate_from": 20000000,
      "fee_rate_to": 1000,
      "amount_negotiable": true,
      "rate_negotiable": false,
      "auto_accept_type": 1,
      "time_valid": 1200,
      "rate": 0.0007488487289581015,
      "proof_address": "",
      "addr_from": "Phsv1FLLgPk3ZwS8gLUv1LZbHTpLti7fzK",
      "bid_count": 0,
      "highest_bid": null
    },
    {
      "msg_id": "000000006a379ba0dd5238bba177f73c51ebc3cf3ded9265efc9432f",
      "timestamp": 1782029216,
      "protocol_version": 4,
      "coin_from": "PART",
      "coin_to": "XMR",
      "coin_from_id": 1,
      "coin_to_id": 6,
      "amount_from": 200000000000,
      "amount_to": 2000000000000,
      "amount_from_str": "2000.00000000",
      "amount_to_str": "2.000000000000",
      "min_bid_amount": 5000000000,
      "min_bid_amount_str": "50.00000000",
      "swap_type": 5,
      "lock_type": 2,
      "lock_value": 86400,
      "fee_rate_from": 200000,
      "fee_rate_to": 20000000,
      "amount_negotiable": true,
      "rate_negotiable": false,
      "auto_accept_type": 1,
      "time_valid": 600,
      "rate": 10.0,
      "proof_address": "",
      "addr_from": "PgjzeVki3NRtSyd2EmsDe1B4bu83cxAACm",
      "bid_count": 0,
      "highest_bid": null
    },
    {
      "msg_id": "000000006a379bb4b05792a6b28585ae8e58d56f7e31d4940cba8b78",
      "timestamp": 1782029236,
      "protocol_version": 4,
      "coin_from": "BTC",
      "coin_to": "XMR",
      "coin_from_id": 2,
      "coin_to_id": 6,
      "amount_from": 1400000,
      "amount_to": 2797472373540,
      "amount_from_str": "0.01400000",
      "amount_to_str": "2.797472373540",
      "min_bid_amount": 500000,
      "min_bid_amount_str": "0.00500000",
      "swap_type": 5,
      "lock_type": 2,
      "lock_value": 86400,
      "fee_rate_from": 2000,
      "fee_rate_to": 20000000,
      "amount_negotiable": true,
      "rate_negotiable": false,
      "auto_accept_type": 1,
      "time_valid": 720,
      "rate": 1998194.5525285713,
      "proof_address": "",
      "addr_from": "PpKVaErCgmrQGZLdV79F1sb2JMa7cEtVYG",
      "bid_count": 0,
      "highest_bid": null
    },
    {
      "msg_id": "000000006a379bd66ae8b1a1d26a48b928d33651fbc916256b4daa59",
      "timestamp": 1782029270,
      "protocol_version": 4,
      "coin_from": "WOW",
      "coin_to": "LTC",
      "coin_from_id": 9,
      "coin_to_id": 3,
      "amount_from": 1000000000000000,
      "amount_to": 415750000,
      "amount_from_str": "10000.00000000000",
      "amount_to_str": "4.15750000",
      "min_bid_amount": 500000000000000,
      "min_bid_amount_str": "5000.00000000000",
      "swap_type": 5,
      "lock_type": 2,
      "lock_value": 86400,
      "fee_rate_from": 270000000,
      "fee_rate_to": 1000,
      "amount_negotiable": true,
      "rate_negotiable": false,
      "auto_accept_type": 1,
      "time_valid": 14400,
      "rate": 4.1575e-07,
      "proof_address": "",
      "addr_from": "Pt8RResgckUwVQCWj42pK1hQDxYj2297LB",
      "bid_count": 0,
      "highest_bid": null
    },
    {
      "msg_id": "000000006a379be65ce4ae4d29fa8e395beecd140b8ca4863e4c6de3",
      "timestamp": 1782029286,
      "protocol_version": 4,
      "coin_from": "LTC",
      "coin_to": "BTC",
      "coin_from_id": 3,
      "coin_to_id": 2,
      "amount_from": 4928000000,
      "amount_to": 3579502,
      "amount_from_str": "49.28000000",
      "amount_to_str": "0.03579502",
      "min_bid_amount": 500000000,
      "min_bid_amount_str": "5.00000000",
      "swap_type": 5,
      "lock_type": 2,
      "lock_value": 86400,
      "fee_rate_from": 1000,
      "fee_rate_to": 2124,
      "amount_negotiable": true,
      "rate_negotiable": false,
      "auto_accept_type": 1,
      "time_valid": 1200,
      "rate": 0.0007263599837662337,
      "proof_address": "",
      "addr_from": "PeSYic8EHZFJGBX4wUSXW89xpNe1m6fwGq",
      "bid_count": 0,
      "highest_bid": null
    },
    {
      "msg_id": "000000006a379c0be1ddf685d7d2de197cb2520f26faa4b76720e7db",
      "timestamp": 1782029323,
      "protocol_version": 4,
      "coin_from": "LTC",
      "coin_to": "BTC",
      "coin_from_id": 3,
      "coin_to_id": 2,
      "amount_from": 15950000000,
      "amount_to": 15949840,
      "amount_from_str": "159.50000000",
      "amount_to_str": "0.15949840",
      "min_bid_amount": 200000000,
      "min_bid_amount_str": "2.00000000",
      "swap_type": 5,
      "lock_type": 2,
      "lock_value": 86400,
      "fee_rate_from": 1000,
      "fee_rate_to": 2124,
      "amount_negotiable": true,
      "rate_negotiable": false,
      "auto_accept_type": 1,
      "time_valid": 3600,
      "rate": 0.0009999899686520377,
      "proof_address": "",
      "addr_from": "PhVKRZM2sJuzUwJ8RhsfzxM2UDxab4RYUC",
      "bid_count": 0,
      "highest_bid": null
    },
    {
      "msg_id": "000000006a379c16acc846431d43350afcdf56c015067cb962bd6f59",
      "timestamp": 1782029334,
      "protocol_version": 4,
      "coin_from": "LTC",
      "coin_to": "XMR",
      "coin_from_id": 3,
      "coin_to_id": 6,
      "amount_from": 45000000,
      "amount_to": 62798016402,
      "amount_from_str": "0.45000000",
      "amount_to_str": "0.062798016402",
      "min_bid_amount": 2000000,
      "min_bid_amount_str": "0.02000000",
      "swap_type": 5,
      "lock_type": 2,
      "lock_value": 86400,
      "fee_rate_from": 1000,
      "fee_rate_to": 20000000,
      "amount_negotiable": true,
      "rate_negotiable": false,
      "auto_accept_type": 1,
      "time_valid": 600,
      "rate": 1395.5114756,
      "proof_address": "",
      "addr_from": "PgToDGNbv82pk1UQitvZwmVQbjfkSUuV4m",
      "bid_count": 0,
      "highest_bid": null
    },
    {
      "msg_id": "000000006a379c2c7ff6b5ae0a19e12a2673a84c46e37872106c950c",
      "timestamp": 1782029356,
      "protocol_version": 4,
      "coin_from": "XMR",
      "coin_to": "BTC",
      "coin_from_id": 6,
      "coin_to_id": 2,
      "amount_from": 710000000000,
      "amount_to": 368827,
      "amount_from_str": "0.710000000000",
      "amount_to_str": "0.00368827",
      "min_bid_amount": 1000000000,
      "min_bid_amount_str": "0.001000000000",
      "swap_type": 5,
      "lock_type": 2,
      "lock_value": 86400,
      "fee_rate_from": 20000000,
      "fee_rate_to": 2124,
      "amount_negotiable": true,
      "rate_negotiable": false,
      "auto_accept_type": 1,
      "time_valid": 3600,
      "rate": 5.19474647887324e-07,
      "proof_address": "",
      "addr_from": "PvYrychrvrPoXkJZymR1VFEkJU3dcviYvB",
      "bid_count": 0,
      "highest_bid": null
    },
    {
      "msg_id": "000000006a379c63c62bfd7201558cdb9e0d546313b4655ac6502202",
      "timestamp": 1782029411,
      "protocol_version": 4,
      "coin_from": "XMR",
      "coin_to": "LTC",
      "coin_from_id": 6,
      "coin_to_id": 3,
      "amount_from": 41000000000,
      "amount_to": 30351932,
      "amount_from_str": "0.041000000000",
      "amount_to_str": "0.30351932",
      "min_bid_amount": 10000000000,
      "min_bid_amount_str": "0.010000000000",
      "swap_type": 5,
      "lock_type": 2,
      "lock_value": 86400,
      "fee_rate_from": 20000000,
      "fee_rate_to": 1000,
      "amount_negotiable": true,
      "rate_negotiable": false,
      "auto_accept_type": 1,
      "time_valid": 600,
      "rate": 0.0007402910243902439,
      "proof_address": "",
      "addr_from": "PfWJ5cqoNaFzzEzg9dVfY878aQGKF7nuhh",
      "bid_count": 0,
      "highest_bid": null
    },
    {
      "msg_id": "000000006a379c8ecaf50dfee23fe2d894281e5faeadd51eec1dd44c",
      "timestamp": 1782029454,
      "protocol_version": 4,
      "coin_from": "PART",
      "coin_to": "LTC",
      "coin_from_id": 1,
      "coin_to_id": 3,
      "amount_from": 200000000000,
      "amount_to": 930956000,
      "amount_from_str": "2000.00000000",
      "amount_to_str": "9.30956000",
      "min_bid_amount": 5000000000,
      "min_bid_amount_str": "50.00000000",
      "swap_type": 5,
      "lock_type": 2,
      "lock_value": 86400,
      "fee_rate_from": 200000,
      "fee_rate_to": 1000,
      "amount_negotiable": true,
      "rate_negotiable": false,
      "auto_accept_type": 1,
      "time_valid": 600,
      "rate": 0.00465478,
      "proof_address": "",
      "addr_from": "PmRtQgaHJHsTbvEuAqyE4agGryGHEYmeih",
      "bid_count": 0,
      "highest_bid": null
    },
    {
      "msg_id": "000000006a379c9b7d00e647dc02f4fa9db9f35e0b2830c8b55bc359",
      "timestamp": 1782029467,
      "protocol_version": 4,
      "coin_from": "WOW",
      "coin_to": "BTC",
      "coin_from_id": 9,
      "coin_to_id": 2,
      "amount_from": 1000000000000000,
      "amount_to": 290000,
      "amount_from_str": "10000.00000000000",
      "amount_to_str": "0.00290000",
      "min_bid_amount": 500000000000000,
      "min_bid_amount_str": "5000.00000000000",
      "swap_type": 5,
      "lock_type": 2,
      "lock_value": 86400,
      "fee_rate_from": 270000000,
      "fee_rate_to": 2124,
      "amount_negotiable": true,
      "rate_negotiable": false,
      "auto_accept_type": 1,
      "time_valid": 14400,
      "rate": 2.9e-10,
      "proof_address": "",
      "addr_from": "PZQm4kx5P1QZJsE56VdtdkZkLwTMnijPTy",
      "bid_count": 0,
      "highest_bid": null
    },
    {
      "msg_id": "000000006a379cd096c6470029ad27d5174f91d9f95acb0842584751",
      "timestamp": 1782029520,
      "protocol_version": 4,
      "coin_from": "FIRO",
      "coin_to": "LTC",
      "coin_from_id": 13,
      "coin_to_id": 3,
      "amount_from": 34500000000,
      "amount_to": 1107397560,
      "amount_from_str": "345.00000000",
      "amount_to_str": "11.07397560",
      "min_bid_amount": 500000000,
      "min_bid_amount_str": "5.00000000",
      "swap_type": 5,
      "lock_type": 2,
      "lock_value": 86400,
      "fee_rate_from": 1010,
      "fee_rate_to": 1000,
      "amount_negotiable": true,
      "rate_negotiable": false,
      "auto_accept_type": 1,
      "time_valid": 660,
      "rate": 0.03209848,
      "proof_address": "",
      "addr_from": "Pmz4XKbUsrYKKSSoqoqVDYtEnVnH6GEF69",
      "bid_count": 0,
      "highest_bid": null
    },
    {
      "msg_id": "000000006a379cd0e9397b243f45afc85da20bb920236269a1a86622",
      "timestamp": 1782029520,
      "protocol_version": 4,
      "coin_from": "BTC",
      "coin_to": "XMR",
      "coin_from_id": 2,
      "coin_to_id": 6,
      "amount_from": 31500000,
      "amount_to": 63917947484403,
      "amount_from_str": "0.31500000",
      "amount_to_str": "63.917947484403",
      "min_bid_amount": 1000000,
      "min_bid_amount_str": "0.01000000",
      "swap_type": 5,
      "lock_type": 2,
      "lock_value": 86400,
      "fee_rate_from": 2000,
      "fee_rate_to": 20000000,
      "amount_negotiable": true,
      "rate_negotiable": false,
      "auto_accept_type": 1,
      "time_valid": 650,
      "rate": 2029141.1899810475,
      "proof_address": "",
      "addr_from": "PefVzdZyHqr3sMxvfEbwhoyjTxdoQPdUwf",
      "bid_count": 0,
      "highest_bid": null
    },
    {
      "msg_id": "000000006a379cf660b304b8c47ded3eb8df6fbec675a323a57194bd",
      "timestamp": 1782029558,
      "protocol_version": 4,
      "coin_from": "BTC",
      "coin_to": "WOW",
      "coin_from_id": 2,
      "coin_to_id": 9,
      "amount_from": 500000,
      "amount_to": 8606913999344695,
      "amount_from_str": "0.00500000",
      "amount_to_str": "86069.13999344695",
      "min_bid_amount": 100000,
      "min_bid_amount_str": "0.00100000",
      "swap_type": 5,
      "lock_type": 2,
      "lock_value": 86400,
      "fee_rate_from": 2124,
      "fee_rate_to": 270000000,
      "amount_negotiable": true,
      "rate_negotiable": false,
      "auto_accept_type": 1,
      "time_valid": 14400,
      "rate": 17213827998.68939,
      "proof_address": "",
      "addr_from": "Pr7dmDgZ3p6b1H3Hw7GoCTrrqf4ebWu2ch",
      "bid_count": 0,
      "highest_bid": null
    },
    {
      "msg_id": "000000006a379dd8abf920c2acc62e1eef2d0d11e7fcb76b8fac3d98",
      "timestamp": 1782029784,
      "protocol_version": 4,
      "coin_from": "XMR",
      "coin_to": "BTC",
      "coin_from_id": 6,
      "coin_to_id": 2,
      "amount_from": 45000000000000,
      "amount_to": 23382000,
      "amount_from_str": "45.000000000000",
      "amount_to_str": "0.23382000",
      "min_bid_amount": 1000000000000,
      "min_bid_amount_str": "1.000000000000",
      "swap_type": 5,
      "lock_type": 2,
      "lock_value": 86400,
      "fee_rate_from": 20000000,
      "fee_rate_to": 2000,
      "amount_negotiable": true,
      "rate_negotiable": false,
      "auto_accept_type": 1,
      "time_valid": 600,
      "rate": 5.196e-07,
      "proof_address": "",
      "addr_from": "Pn3TpHNTuV531JmpRmC6MFaQxgnGMFogyM",
      "bid_count": 0,
      "highest_bid": null
    },
    {
      "msg_id": "000000006a379e2a6592d74edeaaf07c9b89c99b0f9e19be422996fd",
      "timestamp": 1782029866,
      "protocol_version": 4,
      "coin_from": "LTC",
      "coin_to": "PART_BLIND",
      "coin_from_id": 3,
      "coin_to_id": 7,
      "amount_from": 270000000,
      "amount_to": 123058968060,
      "amount_from_str": "2.70000000",
      "amount_to_str": "1230.58968060",
      "min_bid_amount": 1000000,
      "min_bid_amount_str": "0.01000000",
      "swap_type": 5,
      "lock_type": 2,
      "lock_value": 86400,
      "fee_rate_from": 1000,
      "fee_rate_to": 200000,
      "amount_negotiable": true,
      "rate_negotiable": false,
      "auto_accept_type": 1,
      "time_valid": 1200,
      "rate": 455.77395577777776,
      "proof_address": "",
      "addr_from": "PdZ7kX1168Kw6uFsWjPMshq88VwDWRiyE6",
      "bid_count": 0,
      "highest_bid": null
    },
    {
      "msg_id": "000000006a379e331f31a93a75666acd0cdf9fa304889eb63180ca0d",
      "timestamp": 1782029875,
      "protocol_version": 4,
      "coin_from": "XMR",
      "coin_to": "BTC",
      "coin_from_id": 6,
      "coin_to_id": 2,
      "amount_from": 10169000000000,
      "amount_to": 5202134,
      "amount_from_str": "10.169000000000",
      "amount_to_str": "0.05202134",
      "min_bid_amount": 100000000000,
      "min_bid_amount_str": "0.100000000000",
      "swap_type": 5,
      "lock_type": 2,
      "lock_value": 86400,
      "fee_rate_from": 20000000,
      "fee_rate_to": 2000,
      "amount_negotiable": true,
      "rate_negotiable": false,
      "auto_accept_type": 1,
      "time_valid": 900,
      "rate": 5.115679024486183e-07,
      "proof_address": "",
      "addr_from": "PvukyPENoukeGbusgQcu8UY5diMG2361yn",
      "bid_count": 0,
      "highest_bid": null
    },
    {
      "msg_id": "000000006a379e481541e605046c080bf0359c412a1e6ae3fa4ec2ec",
      "timestamp": 1782029896,
      "protocol_version": 4,
      "coin_from": "PART",
      "coin_to": "XMR",
      "coin_from_id": 1,
      "coin_to_id": 6,
      "amount_from": 200000000000,
      "amount_to": 2000000000000,
      "amount_from_str": "2000.00000000",
      "amount_to_str": "2.000000000000",
      "min_bid_amount": 5000000000,
      "min_bid_amount_str": "50.00000000",
      "swap_type": 5,
      "lock_type": 2,
      "lock_value": 86400,
      "fee_rate_from": 200000,
      "fee_rate_to": 20000000,
      "amount_negotiable": true,
      "rate_negotiable": false,
      "auto_accept_type": 1,
      "time_valid": 600,
      "rate": 10.0,
      "proof_address": "",
      "addr_from": "PiHVBveMy5yfU4vZh46vv7QeUf9bUEhyij",
      "bid_count": 0,
      "highest_bid": null
    },
    {
      "msg_id": "000000006a379e4d66cc4aee76d7ec839d8af2e998c3febb9f253208",
      "timestamp": 1782029901,
      "protocol_version": 4,
      "coin_from": "DASH",
      "coin_to": "PART",
      "coin_from_id": 12,
      "coin_to_id": 1,
      "amount_from": 362795999,
      "amount_to": 148749179850,
      "amount_from_str": "3.62795999",
      "amount_to_str": "1487.49179850",
      "min_bid_amount": 100000,
      "min_bid_amount_str": "0.00100000",
      "swap_type": 5,
      "lock_type": 2,
      "lock_value": 43200,
      "fee_rate_from": 1000,
      "fee_rate_to": 200000,
      "amount_negotiable": true,
      "rate_negotiable": false,
      "auto_accept_type": 0,
      "time_valid": 3600,
      "rate": 410.00777367999586,
      "proof_address": "",
      "addr_from": "PgTfpGmwtXppGVrNUAdJicKAVErZBEK2xo",
      "bid_count": 0,
      "highest_bid": null
    },
    {
      "msg_id": "000000006a379e4d5584d297cfda44133b54b582f3621e3e373f5c66",
      "timestamp": 1782029901,
      "protocol_version": 4,
      "coin_from": "PIVX",
      "coin_to": "LTC",
      "coin_from_id": 11,
      "coin_to_id": 3,
      "amount_from": 2995328135515,
      "amount_to": 3055527671,
      "amount_from_str": "29953.28135515",
      "amount_to_str": "30.55527671",
      "min_bid_amount": 100000,
      "min_bid_amount_str": "0.00100000",
      "swap_type": 5,
      "lock_type": 2,
      "lock_value": 43200,
      "fee_rate_from": 10000,
      "fee_rate_to": 1000,
      "amount_negotiable": true,
      "rate_negotiable": false,
      "auto_accept_type": 0,
      "time_valid": 3600,
      "rate": 0.0010200978099097814,
      "proof_address": "",
      "addr_from": "PgTfpGmwtXppGVrNUAdJicKAVErZBEK2xo",
      "bid_count": 0,
      "highest_bid": null
    },
    {
      "msg_id": "000000006a379e4d16153270d035343b6e590fab2d1c626db504bcf6",
      "timestamp": 1782029901,
      "protocol_version": 4,
      "coin_from": "PIVX",
      "coin_to": "PART",
      "coin_from_id": 11,
      "coin_to_id": 1,
      "amount_from": 2691429564989,
      "amount_to": 1341501708322,
      "amount_from_str": "26914.29564989",
      "amount_to_str": "13415.01708322",
      "min_bid_amount": 100000,
      "min_bid_amount_str": "0.00100000",
      "swap_type": 5,
      "lock_type": 2,
      "lock_value": 43200,
      "fee_rate_from": 10000,
      "fee_rate_to": 200000,
      "amount_negotiable": true,
      "rate_negotiable": false,
      "auto_accept_type": 0,
      "time_valid": 3600,
      "rate": 0.49843463331632193,
      "proof_address": "",
      "addr_from": "PgTfpGmwtXppGVrNUAdJicKAVErZBEK2xo",
      "bid_count": 0,
      "highest_bid": null
    },
    {
      "msg_id": "000000006a379e4f9d8015067b531915f00ff545ed34c3be75c9bdc4",
      "timestamp": 1782029903,
      "protocol_version": 4,
      "coin_from": "XMR",
      "coin_to": "LTC",
      "coin_from_id": 6,
      "coin_to_id": 3,
      "amount_from": 40774478820000,
      "amount_to": 30993702952,
      "amount_from_str": "40.774478820000",
      "amount_to_str": "309.93702952",
      "min_bid_amount": 1000000000,
      "min_bid_amount_str": "0.001000000000",
      "swap_type": 5,
      "lock_type": 2,
      "lock_value": 43200,
      "fee_rate_from": 20000000,
      "fee_rate_to": 1000,
      "amount_negotiable": true,
      "rate_negotiable": false,
      "auto_accept_type": 0,
      "time_valid": 3600,
      "rate": 0.0007601250549105117,
      "proof_address": "",
      "addr_from": "PgTfpGmwtXppGVrNUAdJicKAVErZBEK2xo",
      "bid_count": 0,
      "highest_bid": null
    },
    {
      "msg_id": "000000006a379e4f961ad1769f4aff888dc8cc422881e1644f460bc2",
      "timestamp": 1782029903,
      "protocol_version": 4,
      "coin_from": "BTC",
      "coin_to": "LTC",
      "coin_from_id": 2,
      "coin_to_id": 3,
      "amount_from": 50415742,
      "amount_to": 73754360035,
      "amount_from_str": "0.50415742",
      "amount_to_str": "737.54360035",
      "min_bid_amount": 100000,
      "min_bid_amount_str": "0.00100000",
      "swap_type": 5,
      "lock_type": 2,
      "lock_value": 43200,
      "fee_rate_from": 2124,
      "fee_rate_to": 1000,
      "amount_negotiable": true,
      "rate_negotiable": false,
      "auto_accept_type": 0,
      "time_valid": 3600,
      "rate": 1462.92322812585,
      "proof_address": "",
      "addr_from": "PgTfpGmwtXppGVrNUAdJicKAVErZBEK2xo",
      "bid_count": 0,
      "highest_bid": null
    },
    {
      "msg_id": "000000006a379e4f4a2cbe50c6b274b8e2e1b6e992d856456cd8336e",
      "timestamp": 1782029903,
      "protocol_version": 4,
      "coin_from": "DASH",
      "coin_to": "LTC",
      "coin_from_id": 12,
      "coin_to_id": 3,
      "amount_from": 626819719,
      "amount_to": 525518052,
      "amount_from_str": "6.26819719",
      "amount_to_str": "5.25518052",
      "min_bid_amount": 100000,
      "min_bid_amount_str": "0.00100000",
      "swap_type": 5,
      "lock_type": 2,
      "lock_value": 43200,
      "fee_rate_from": 1000,
      "fee_rate_to": 1000,
      "amount_negotiable": true,
      "rate_negotiable": false,
      "auto_accept_type": 0,
      "time_valid": 3600,
      "rate": 0.8383878746482128,
      "proof_address": "",
      "addr_from": "PgTfpGmwtXppGVrNUAdJicKAVErZBEK2xo",
      "bid_count": 0,
      "highest_bid": null
    },
    {
      "msg_id": "000000006a379e503ea7c0697d851e4fa5ab5b80ede135075fa8a57b",
      "timestamp": 1782029904,
      "protocol_version": 4,
      "coin_from": "LTC",
      "coin_to": "BTC",
      "coin_from_id": 3,
      "coin_to_id": 2,
      "amount_from": 14748091622,
      "amount_to": 10542687,
      "amount_from_str": "147.48091622",
      "amount_to_str": "0.10542687",
      "min_bid_amount": 100000,
      "min_bid_amount_str": "0.00100000",
      "swap_type": 5,
      "lock_type": 2,
      "lock_value": 43200,
      "fee_rate_from": 1000,
      "fee_rate_to": 2124,
      "amount_negotiable": true,
      "rate_negotiable": false,
      "auto_accept_type": 0,
      "time_valid": 3600,
      "rate": 0.0007148509292058695,
      "proof_address": "",
      "addr_from": "PgTfpGmwtXppGVrNUAdJicKAVErZBEK2xo",
      "bid_count": 0,
      "highest_bid": null
    },
    {
      "msg_id": "000000006a379e509f7e235e5437b4bd34c9fdceabf489fabbd89dcd",
      "timestamp": 1782029904,
      "protocol_version": 4,
      "coin_from": "PIVX",
      "coin_to": "BTC",
      "coin_from_id": 11,
      "coin_to_id": 2,
      "amount_from": 2995352399203,
      "amount_to": 2136103,
      "amount_from_str": "29953.52399203",
      "amount_to_str": "0.02136103",
      "min_bid_amount": 100000,
      "min_bid_amount_str": "0.00100000",
      "swap_type": 5,
      "lock_type": 2,
      "lock_value": 43200,
      "fee_rate_from": 10000,
      "fee_rate_to": 2124,
      "amount_negotiable": true,
      "rate_negotiable": false,
      "auto_accept_type": 0,
      "time_valid": 3600,
      "rate": 7.131391286609121e-07,
      "proof_address": "",
      "addr_from": "PgTfpGmwtXppGVrNUAdJicKAVErZBEK2xo",
      "bid_count": 0,
      "highest_bid": null
    },
    {
      "msg_id": "000000006a379e5053a287fd077c3f9aa6a6ae4770159217780d72fc",
      "timestamp": 1782029904,
      "protocol_version": 4,
      "coin_from": "LTC",
      "coin_to": "XMR",
      "coin_from_id": 3,
      "coin_to_id": 6,
      "amount_from": 14747083224,
      "amount_to": 20954834324100,
      "amount_from_str": "147.47083224",
      "amount_to_str": "20.954834324100",
      "min_bid_amount": 100000,
      "min_bid_amount_str": "0.00100000",
      "swap_type": 5,
      "lock_type": 2,
      "lock_value": 43200,
      "fee_rate_from": 1000,
      "fee_rate_to": 20000000,
      "amount_negotiable": true,
      "rate_negotiable": false,
      "auto_accept_type": 0,
      "time_valid": 3600,
      "rate": 1420.9477227332152,
      "proof_address": "",
      "addr_from": "PgTfpGmwtXppGVrNUAdJicKAVErZBEK2xo",
      "bid_count": 0,
      "highest_bid": null
    },
    {
      "msg_id": "000000006a379e505322afbf764b5aca21d4e46a271e4ea7f4fa002a",
      "timestamp": 1782029904,
      "protocol_version": 4,
      "coin_from": "BTC",
      "coin_to": "XMR",
      "coin_from_id": 2,
      "coin_to_id": 6,
      "amount_from": 50549977,
      "amount_to": 102770655885160,
      "amount_from_str": "0.50549977",
      "amount_to_str": "102.770655885160",
      "min_bid_amount": 100000,
      "min_bid_amount_str": "0.00100000",
      "swap_type": 5,
      "lock_type": 2,
      "lock_value": 43200,
      "fee_rate_from": 2124,
      "fee_rate_to": 20000000,
      "amount_negotiable": true,
      "rate_negotiable": false,
      "auto_accept_type": 0,
      "time_valid": 3600,
      "rate": 2033050.4974346478,
      "proof_address": "",
      "addr_from": "PgTfpGmwtXppGVrNUAdJicKAVErZBEK2xo",
      "bid_count": 0,
      "highest_bid": null
    },
    {
      "msg_id": "000000006a379e53f1dba0059449096f9a80e528f20886694a468031",
      "timestamp": 1782029907,
      "protocol_version": 4,
      "coin_from": "XMR",
      "coin_to": "BTC",
      "coin_from_id": 6,
      "coin_to_id": 2,
      "amount_from": 40831360010000,
      "amount_to": 21695854,
      "amount_from_str": "40.831360010000",
      "amount_to_str": "0.21695854",
      "min_bid_amount": 1000000000,
      "min_bid_amount_str": "0.001000000000",
      "swap_type": 5,
      "lock_type": 2,
      "lock_value": 43200,
      "fee_rate_from": 20000000,
      "fee_rate_to": 2124,
      "amount_negotiable": true,
      "rate_negotiable": false,
      "auto_accept_type": 0,
      "time_valid": 3600,
      "rate": 5.313527150378159e-07,
      "proof_address": "",
      "addr_from": "PgTfpGmwtXppGVrNUAdJicKAVErZBEK2xo",
      "bid_count": 0,
      "highest_bid": null
    },
    {
      "msg_id": "000000006a379e534e37769577d7a6c947ab4a8fbbb646078303f45d",
      "timestamp": 1782029907,
      "protocol_version": 4,
      "coin_from": "DASH",
      "coin_to": "BTC",
      "coin_from_id": 12,
      "coin_to_id": 2,
      "amount_from": 626820563,
      "amount_to": 367387,
      "amount_from_str": "6.26820563",
      "amount_to_str": "0.00367387",
      "min_bid_amount": 100000,
      "min_bid_amount_str": "0.00100000",
      "swap_type": 5,
      "lock_type": 2,
      "lock_value": 43200,
      "fee_rate_from": 1000,
      "fee_rate_to": 2124,
      "amount_negotiable": true,
      "rate_negotiable": false,
      "auto_accept_type": 0,
      "time_valid": 3600,
      "rate": 0.0005861119141364225,
      "proof_address": "",
      "addr_from": "PgTfpGmwtXppGVrNUAdJicKAVErZBEK2xo",
      "bid_count": 0,
      "highest_bid": null
    },
    {
      "msg_id": "000000006a379e5383ad0d905f48f64b7da46280b7ccbd0d008045fa",
      "timestamp": 1782029907,
      "protocol_version": 4,
      "coin_from": "BTC",
      "coin_to": "DASH",
      "coin_from_id": 2,
      "coin_to_id": 12,
      "amount_from": 50349756,
      "amount_to": 89875085514,
      "amount_from_str": "0.50349756",
      "amount_to_str": "898.75085514",
      "min_bid_amount": 100000,
      "min_bid_amount_str": "0.00100000",
      "swap_type": 5,
      "lock_type": 2,
      "lock_value": 43200,
      "fee_rate_from": 2124,
      "fee_rate_to": 1000,
      "amount_negotiable": true,
      "rate_negotiable": false,
      "auto_accept_type": 0,
      "time_valid": 3600,
      "rate": 1785.015313957033,
      "proof_address": "",
      "addr_from": "PgTfpGmwtXppGVrNUAdJicKAVErZBEK2xo",
      "bid_count": 0,
      "highest_bid": null
    },
    {
      "msg_id": "000000006a379e5322dd6e4709eb776f005a87693c5d2aae7611de07",
      "timestamp": 1782029907,
      "protocol_version": 4,
      "coin_from": "LTC",
      "coin_to": "DASH",
      "coin_from_id": 3,
      "coin_to_id": 12,
      "amount_from": 14526593308,
      "amount_to": 18118437473,
      "amount_from_str": "145.26593308",
      "amount_to_str": "181.18437473",
      "min_bid_amount": 100000,
      "min_bid_amount_str": "0.00100000",
      "swap_type": 5,
      "lock_type": 2,
      "lock_value": 43200,
      "fee_rate_from": 1000,
      "fee_rate_to": 1000,
      "amount_negotiable": true,
      "rate_negotiable": false,
      "auto_accept_type": 0,
      "time_valid": 3600,
      "rate": 1.2472599107611777,
      "proof_address": "",
      "addr_from": "PgTfpGmwtXppGVrNUAdJicKAVErZBEK2xo",
      "bid_count": 0,
      "highest_bid": null
    },
    {
      "msg_id": "000000006a379e717355169c9bb6e608fb3768a06ad8853a4b7b462a",
      "timestamp": 1782029937,
      "protocol_version": 4,
      "coin_from": "BTC",
      "coin_to": "XMR",
      "coin_from_id": 2,
      "coin_to_id": 6,
      "amount_from": 110000,
      "amount_to": 732600000000,
      "amount_from_str": "0.00110000",
      "amount_to_str": "0.732600000000",
      "min_bid_amount": 100000,
      "min_bid_amount_str": "0.00100000",
      "swap_type": 5,
      "lock_type": 2,
      "lock_value": 86400,
      "fee_rate_from": 2123,
      "fee_rate_to": 20000000,
      "amount_negotiable": true,
      "rate_negotiable": false,
      "auto_accept_type": 1,
      "time_valid": 3600,
      "rate": 6660000.0,
      "proof_address": "",
      "addr_from": "PhTu4nL4Jji2RRXMeEtuNbxSYKCFZXLrE6",
      "bid_count": 0,
      "highest_bid": null
    },
    {
      "msg_id": "000000006a379e8516dbdd1c0a2a213b851ea99490ab9a930196efbb",
      "timestamp": 1782029957,
      "protocol_version": 4,
      "coin_from": "BTC",
      "coin_to": "XMR",
      "coin_from_id": 2,
      "coin_to_id": 6,
      "amount_from": 1400000,
      "amount_to": 2797472373540,
      "amount_from_str": "0.01400000",
      "amount_to_str": "2.797472373540",
      "min_bid_amount": 500000,
      "min_bid_amount_str": "0.00500000",
      "swap_type": 5,
      "lock_type": 2,
      "lock_value": 86400,
      "fee_rate_from": 2000,
      "fee_rate_to": 20000000,
      "amount_negotiable": true,
      "rate_negotiable": false,
      "auto_accept_type": 1,
      "time_valid": 720,
      "rate": 1998194.5525285713,
      "proof_address": "",
      "addr_from": "Pvw9gd9fS1nNZzAPP74ePsTiaUoFH2i6hu",
      "bid_count": 0,
      "highest_bid": null
    },
    {
      "msg_id": "000000006a379e8a1820f9d915e39e1edb4a19567585550964b4cb80",
      "timestamp": 1782029962,
      "protocol_version": 4,
      "coin_from": "LTC",
      "coin_to": "XMR",
      "coin_from_id": 3,
      "coin_to_id": 6,
      "amount_from": 45000000,
      "amount_to": 62828468454,
      "amount_from_str": "0.45000000",
      "amount_to_str": "0.062828468454",
      "min_bid_amount": 2000000,
      "min_bid_amount_str": "0.02000000",
      "swap_type": 5,
      "lock_type": 2,
      "lock_value": 86400,
      "fee_rate_from": 1000,
      "fee_rate_to": 20000000,
      "amount_negotiable": true,
      "rate_negotiable": false,
      "auto_accept_type": 1,
      "time_valid": 600,
      "rate": 1396.1881878666666,
      "proof_address": "",
      "addr_from": "PqKvJCjtexguhSFWoEhidQDTtvP4cVxKhX",
      "bid_count": 0,
      "highest_bid": null
    },
    {
      "msg_id": "000000006a379e9dbeb05253d505f7f339a8f7a5bf0f8018469b617b",
      "timestamp": 1782029981,
      "protocol_version": 4,
      "coin_from": "LTC",
      "coin_to": "XMR",
      "coin_from_id": 3,
      "coin_to_id": 6,
      "amount_from": 365000000,
      "amount_to": 511234968326,
      "amount_from_str": "3.65000000",
      "amount_to_str": "0.511234968326",
      "min_bid_amount": 5000000,
      "min_bid_amount_str": "0.05000000",
      "swap_type": 5,
      "lock_type": 2,
      "lock_value": 86400,
      "fee_rate_from": 1000,
      "fee_rate_to": 20000000,
      "amount_negotiable": true,
      "rate_negotiable": false,
      "auto_accept_type": 1,
      "time_valid": 1200,
      "rate": 1400.6437488383563,
      "proof_address": "",
      "addr_from": "PrDuVjo2wRefYnv4tw2dsaMqNsE6rKbq2w",
      "bid_count": 0,
      "highest_bid": null
    },
    {
      "msg_id": "000000006a379eb5c81bfd2d091e3f6dbb2e10adcfaf49a8e0921fa3",
      "timestamp": 1782030005,
      "protocol_version": 4,
      "coin_from": "LTC",
      "coin_to": "BCH",
      "coin_from_id": 3,
      "coin_to_id": 17,
      "amount_from": 64000000,
      "amount_to": 14548773,
      "amount_from_str": "0.64000000",
      "amount_to_str": "0.14548773",
      "min_bid_amount": 0,
      "min_bid_amount_str": "0.00000000",
      "swap_type": 5,
      "lock_type": 2,
      "lock_value": 7200,
      "fee_rate_from": 1000,
      "fee_rate_to": 1000,
      "amount_negotiable": true,
      "rate_negotiable": false,
      "auto_accept_type": 0,
      "time_valid": 3600,
      "rate": 0.227324578125,
      "proof_address": "",
      "addr_from": "PoT32GAuWctDz8rK3Sd5d6hZ81ib7tFp5c",
      "bid_count": 0,
      "highest_bid": null
    },
    {
      "msg_id": "000000006a379ebbc89a3c8c452916021f49e35e6b3865cb7454e90d",
      "timestamp": 1782030011,
      "protocol_version": 4,
      "coin_from": "WOW",
      "coin_to": "LTC",
      "coin_from_id": 9,
      "coin_to_id": 3,
      "amount_from": 497500000000000,
      "amount_to": 411512100,
      "amount_from_str": "4975.00000000000",
      "amount_to_str": "4.11512100",
      "min_bid_amount": 1000000000000,
      "min_bid_amount_str": "10.00000000000",
      "swap_type": 5,
      "lock_type": 2,
      "lock_value": 86400,
      "fee_rate_from": 270000000,
      "fee_rate_to": 1000,
      "amount_negotiable": true,
      "rate_negotiable": false,
      "auto_accept_type": 1,
      "time_valid": 3600,
      "rate": 8.2716e-07,
      "proof_address": "",
      "addr_from": "Pm47RfnmNvRrwJiQ6sbVc7KBh71BD9mc49",
      "bid_count": 0,
      "highest_bid": null
    },
    {
      "msg_id": "000000006a379edf889e1f9a00273469370bf56c35168db011c0045b",
      "timestamp": 1782030047,
      "protocol_version": 4,
      "coin_from": "XMR",
      "coin_to": "LTC",
      "coin_from_id": 6,
      "coin_to_id": 3,
      "amount_from": 41000000000,
      "amount_to": 30279493,
      "amount_from_str": "0.041000000000",
      "amount_to_str": "0.30279493",
      "min_bid_amount": 10000000000,
      "min_bid_amount_str": "0.010000000000",
      "swap_type": 5,
      "lock_type": 2,
      "lock_value": 86400,
      "fee_rate_from": 20000000,
      "fee_rate_to": 1000,
      "amount_negotiable": true,
      "rate_negotiable": false,
      "auto_accept_type": 1,
      "time_valid": 600,
      "rate": 0.0007385242195121952,
      "proof_address": "",
      "addr_from": "PkVsJqFzQiq19cbyUzAxkyehZSvgpBhdJi",
      "bid_count": 0,
      "highest_bid": null
    }
  ]
}